Workbook

Sheet Rules
A1: RTO Permit | B1: Insu Permit
A2: Private - U/C (4 Wheeler) | B2: Private
A3: Private - U/C EV (4 Wheeler) | B3: Private
A4: Private - BH (4 Wheeler) | B4: Private
A5: Private - BH EV (4 Wheeler) | B5: Private
A6: Goods - G (4 Wheeler) | B6: Goods
A7: Goods - G EV (4 Wheeler) | B7: Goods
A8: Goods - G 3 Ton+ (4 Wheeler) | B8: Goods
A9: Goods - G 3 Ton+ EV (4 Wheeler) | B9: Goods
A10: Goods - G (3 Wheeler) | B10: Goods
A11: Goods - G EV (3 Wheeler) | B11: Goods
A12: Taxi - T (4 Wheeler) | B12: Passenger
... A16: Ambulance (Misc.) | B16: Misc

Sheet Vehicle Info
A1: Model Code | B1: OEM Model | C1: OEM Variant | D1: Segment | E1: Sub Segment | F1: Fuel | G1: Seating | H1: Wheels | I1: Transmission | J1: Drivetrain | K1: Body Make | L1: Body Type | M1: CC | N1: Motor | O1: GVW | P1: GST% | Q1: Permit | R1: Taxi Price | S1: Custom Model | T1: Custom Variant | U1: Display Name | V1: Colour Name | W1: Status | X1: Shield Pack
A2: 1AM2NW1T9MBB1BL | B2: ALFA LOAD DUO | C2: ALFA LC PLUS CNG DUO BSVI BLK | D2: LMM | E2: LMM | F2: CNG | G2: 4 | H2: 3 | I2: MANUAL | J2: RWD | K2: CARGO | L2: COMPLETE | O2: 995 | P2: 0.18 | Q2: GOODS | R2: NO | S2: ALFA LOAD DUO | T2: CNG DUO BSVI | U2: ALFA LOAD DUO CNG BS6 | V2: BLACK | W2: ACTIVE
A3: 1AM2NW1T9MBB1GY | B3: ALFA LOAD DUO | C3: ALFA LC PLUS CNG DUO BSVI GOLD YW | D3: LMM | E3: LMM | F3: CNG | G3: 4 | H3: 3 | I3: MANUAL | J3: RWD | K3: CARGO | L3: COMPLETE | O3: 995 | P3: 0.18 | Q3: GOODS | R3: NO | S3: ALFA LOAD DUO | T3: CNG DUO BSVI | U3: ALFA LOAD DUO CNG BS6 | V3: GOLDEN YELLOW | W3: ACTIVE
A4: 1AM2NW1T9MBB1NB | B4: ALFA LOAD DUO | C4: ALFA LC PLUS CNG DUO BSVI NISS BLU | D4: LMM | E4: LMM | F4: CNG | G4: 4 | H4: 3 | I4: MANUAL | J4: RWD | K4: CARGO | L4: COMPLETE | O4: 995 | P4: 0.18 | Q4: GOODS | R4: NO | S4: ALFA LOAD DUO | T4: CNG DUO BSVI | U4: ALFA LOAD DUO CNG BS6 | V4: NISSAN BLUE | W4: ACTIVE
A5: BH826H1ZH7U6RX | B5: Bolero | C5: B6 BS6.2 - Refresh | D5: PV | E5: NON XUV | F5: DIESEL | G5: 7 | H5: 4 | I5: MANUAL | J5: RWD | K5: SUV | L5: COMPLETE | M5: 1493 | P5: 0.18 | Q5: PRIVATE | R5: YES | S5: BOLERO | T5: B6 BS6.2 - REFRESH | U5: BOLERO B6 BS6.2 - REFRESH | V5: HIGHWAY RED | W5: ACTIVE
A6: BH826H1ZH7U6SK | B6: Bolero | C6: B6 BS6.2 - Refresh | D6: PV | E6: NON XUV | F6: DIESEL | G6: 7 | H6: 4 | I6: MANUAL | J6: RWD | K6: SUV | L6: COMPLETE | M6: 1493 | P6: 0.18 | Q6: PRIVATE | R6: YES | S6: BOLERO | T6: B6 BS6.2 - REFRESH | U6: BOLERO B6 BS6.2 - REFRESH | V6: DSAT SILVER | W6: ACTIVE
A7: BH826H1ZH7U6WD | B7: Bolero | C7: B6 BS6.2 - Refresh | D7: PV | E7: NON XUV | F7: DIESEL | G7: 7 | H7: 4 | I7: MANUAL | J7: RWD | K7: SUV | L7: COMPLETE | M7: 1493 | P7: 0.18 | Q7: PRIVATE | R7: YES | S7: BOLERO | T7: B6 BS6.2 - REFRESH | U7: BOLERO B6 BS6.2 - REFRESH | V7: WHITE | W7: ACTIVE
A8: PFN2FAMMBS6PPFD3WD | B8: MAXX CITY | C8: MAXX CITY 1.4 VXi AC - BS6.2 | D8: CV | E8: CV | F8: DIESEL | G8: 3 | H8: 4 | I8: MANUAL | J8: RWD | K8: CARGO | L8: COMPLETE | O8: 2995 | P8: 0.18 | Q8: GOODS | R8: NO | S8: MAXX CITY | T8: 1.4 VXI AC - BS6.2 | U8: MAXX CITY 1.4 VXI AC - BS6.2 | V8: DIAMOND WHITE | W8: ACTIVE
A9: PFN2FACEBS6PSFD3WD | B9: MAXX CITY | C9: MAXX CITY 1.5 LX BS6.2 | D9: CV | E9: CV | F9: DIESEL | G9: 3 | H9: 4 | I9: MANUAL | J9: RWD | K9: CARGO | L9: COMPLETE | O9: 3120 | P9: 0.18 | Q9: GOODS | R9: NO | S9: MAXX CITY | T9: 1.5 LX BS6.2 | U9: MAXX CITY 1.5 LX BS6.2 | V9: DIAMOND WHITE | W9: ACTIVE
A10: PFN2EABKBS6PSTG3WD | B10: MAXX HD | C10: MAXX HD 1.7 LX CBC BS6.2 - Tipper / Hopper | D10: CV | E10: CV | F10: DIESEL | G10: 3 | H10: 4 | I10: MANUAL | J10: RWD | K10: CARGO | L10: CBC | O10: 3460 | P10: 0.18 | Q10: GOODS | R10: NO | S10: MAXX HD | T10: 1.7 LX CBC BS6.2 - TIPPER / HOPPER | U10: MAXX HD 1.7 LX CBC BS6.2 - TIPPER / HOPPER | V10: WHITE | W10: ACTIVE
A11: PFN2EDDNBS6PPFD3WD | B11: MAXX HD | C11: MAXX HD 1.7 MXi BS6.2 | D11: CV | E11: CV | F11: DIESEL | G11: 3 | H11: 4 | I11: MANUAL | J11: RWD | K11: CARGO | L11: COMPLETE | O11: 3460 | P11: 0.18 | Q11: GOODS | R11: NO | S11: MAXX HD | T11: 1.7 MXI BS6.2 | U11: MAXX HD 1.7 MXI BS6.2 | V11: WHITE | W11: ACTIVE
A12: PFN2EADMBS6PPFD3WD | B12: MAXX HD | C12: MAXX HD 1.7 VXi AC - BS6.2 | D12: CV | E12: CV | F12: DIESEL | G12: 3 | H12: 4 | I12: MANUAL | J12: RWD | K12: CARGO | L12: COMPLETE | O12: 3460 | P12: 0.18 | Q12: GOODS | R12: NO | S12: MAXX HD | T12: 1.7 VXI AC - BS6.2 | U12: MAXX HD 1.7 VXI AC - BS6.2 | V12: WHITE | W12: ACTIVE
A13: PJN2EXCKBS6PSFD3WD | B13: MAXX HD | C13: MAXX HD 1.7L LX BS6.2 | D13: CV | E13: CV | F13: DIESEL | G13: 3 | H13: 4 | I13: MANUAL | J13: RWD | K13: CARGO | L13: COMPLETE | O13: 3460 | P13: 0.18 | Q13: GOODS | R13: NO | S13: MAXX HD | T13: 1.7L LX BS6.2 | U13: MAXX HD 1.7L LX BS6.2 | V13: WHITE | W13: ACTIVE
A14: PKN2ADCMBS6PSNC5CB | B14: PICKUP | C14: BOL CAMPER GOLD RXD BS6.2 - Refresh | D14: CV | E14: CV | F14: DIESEL | G14: 5 | H14: 4 | I14: MANUAL | J14: RWD | K14: CARGO | L14: COMPLETE | O14: 2735 | P14: 0.18 | Q14: GOODS | R14: NO | S14: CAMPER | T14: GOLD RXD BS6.2 - REFRESH | U14: CAMPER GOLD RXD BS6.2 - REFRESH | V14: JAVA BROWN | W14: ACTIVE
A15: PKN2ADCMBS6PSNC5WD | B15: PICKUP | C15: BOL CAMPER GOLD RXD BS6.2 - Refresh | D15: CV | E15: CV | F15: DIESEL | G15: 5 | H15: 4 | I15: MANUAL | J15: RWD | K15: CARGO | L15: COMPLETE | O15: 2735 | P15: 0.18 | Q15: GOODS | R15: NO | S15: CAMPER | T15: GOLD RXD BS6.2 - REFRESH | U15: CAMPER GOLD RXD BS6.2 - REFRESH | V15: WHITE | W15: ACTIVE
A16: PKN2ADC2BS6PSNC5WD | B16: PICKUP | C16: BOL CAMPER GOLD RXD BS6.2 CV - Refresh | D16: CV | E16: CV | F16: DIESEL | G16: 5 | H16: 4 | I16: MANUAL | J16: RWD | K16: CARGO | L16: COMPLETE | O16: 2735 | P16: 0.18 | Q16: GOODS | R16: NO | S16: CAMPER | T16: GOLD RXD BS6.2 CV - REFRESH | U16: CAMPER GOLD RXD BS6.2 CV - REFRESH | V16: WHITE | W16: ACTIVE
A17: SSS24MJA7R8E6WQ | B17: Scorpio | C17: Classic S11 BS6.2 - E | D17: PV | E17: NON XUV | F17: DIESEL | G17: 7 | H17: 4 | I17: MANUAL | J17: RWD | K17: SUV | L17: COMPLETE | M17: 2184 | P17: 0.4 | Q17: PRIVATE | R17: YES | S17: SCORPIO | T17: CLASSIC S11 BS6.2 - E | U17: SCORPIO CLASSIC S11 BS6.2 - E | V17: EVEREST WHITE | W17: ACTIVE
A18: SSS24MJA7R8E7QK | B18: Scorpio | C18: Classic S11 BS6.2 - E | D18: PV | E18: NON XUV | F18: DIESEL | G18: 7 | H18: 4 | I18: MANUAL | J18: RWD | K18: SUV | L18: COMPLETE | M18: 2184 | P18: 0.4 | Q18: PRIVATE | R18: YES | S18: SCORPIO | T18: CLASSIC S11 BS6.2 - E | U18: SCORPIO CLASSIC S11 BS6.2 - E | V18: GALAXY GREY | W18: ACTIVE
A19: SSS24MJA7R8E6QK | B19: Scorpio | C19: Classic S11 BS6.2 - E | D19: PV | E19: NON XUV | F19: DIESEL | G19: 7 | H19: 4 | I19: MANUAL | J19: RWD | K19: SUV | L19: COMPLETE | M19: 2184 | P19: 0.4 | Q19: PRIVATE | R19: YES | S19: SCORPIO | T19: CLASSIC S11 BS6.2 - E | U19: SCORPIO CLASSIC S11 BS6.2 - E | V19: GALAXY GREY | W19: ACTIVE
A20: SSS24MJA7R8E7WQ | B20: Scorpio | C20: Classic S11 BS6.2 - E | D20: PV | E20: NON XUV | F20: DIESEL | G20: 7 | H20: 4 | I20: MANUAL | J20: RWD | K20: SUV | L20: COMPLETE | M20: 2184 | P20: 0.4 | Q20: PRIVATE | R20: YES | S20: SCORPIO | T20: CLASSIC S11 BS6.2 - E | U20: SCORPIO CLASSIC S11 BS6.2 - E | V20: EVEREST WHITE | W20: ACTIVE
A21: AZ1116YJT2A4FA01WQ | B21: Scorpio-N | C21: Z2 D MT 2WD 7 STR - E BS6.2 - New | D21: PV | E21: NON XUV | F21: DIESEL | G21: 7 | H21: 4 | I21: MANUAL | J21: RWD | K21: SUV | L21: COMPLETE | M21: 2198 | P21: 0.4 | Q21: PRIVATE | R21: YES | S21: SCORPIO-N | T21: Z2 D MT 2WD 7 STR - E BS6.2 - NEW | U21: SCORPIO-N Z2 D MT 2WD 7 STR - E BS6.2 - NEW | V21: EVEREST WHITE | W21: ACTIVE
A22: AZ1116YJT2A4FA01XJ | B22: Scorpio-N | C22: Z2 D MT 2WD 7 STR - E BS6.2 - New | D22: PV | E22: NON XUV | F22: DIESEL | G22: 7 | H22: 4 | I22: MANUAL | J22: RWD | K22: SUV | L22: COMPLETE | M22: 2198 | P22: 0.4 | Q22: PRIVATE | R22: YES | S22: SCORPIO-N | T22: Z2 D MT 2WD 7 STR - E BS6.2 - NEW | U22: SCORPIO-N Z2 D MT 2WD 7 STR - E BS6.2 - NEW | V22: STEALTH BLACK | W22: ACTIVE
A23: AZ1116YJT2A4FA01SG | B23: Scorpio-N | C23: Z2 D MT 2WD 7 STR - E BS6.2 - New | D23: PV | E23: NON XUV | F23: DIESEL | G23: 7 | H23: 4 | I23: MANUAL | J23: RWD | K23: SUV | L23: COMPLETE | M23: 2198 | P23: 0.4 | Q23: PRIVATE | R23: YES | S23: SCORPIO-N | T23: Z2 D MT 2WD 7 STR - E BS6.2 - NEW | U23: SCORPIO-N Z2 D MT 2WD 7 STR - E BS6.2 - NEW | V23: VALARIAN SILVER | W23: ACTIVE
A24: AW5068ZAT2B1UC01QL | B24: Thar | C24: LXT P MT 4WD 4S HT BS6.2 | D24: PV | E24: NON XUV | F24: PETROL | G24: 4 | H24: 4 | I24: MANUAL | J24: 4WD | K24: SUV | L24: COMPLETE | M24: 1997 | P24: 0.4 | Q24: PRIVATE | R24: YES | S24: THAR | T24: LXT P MT 4WD 4S HT BS6.2 | U24: THAR LXT P MT 4WD 4S HT BS6.2 | V24: BATTLESHIP GREY | W24: ACTIVE
A25: AW5068ZAT2B1UC01RQ | B25: Thar | C25: LXT P MT 4WD 4S HT BS6.2 | D25: PV | E25: NON XUV | F25: PETROL | G25: 4 | H25: 4 | I25: MANUAL | J25: 4WD | K25: SUV | L25: COMPLETE | M25: 1997 | P25: 0.4 | Q25: PRIVATE | R25: YES | S25: THAR | T25: LXT P MT 4WD 4S HT BS6.2 | U25: THAR LXT P MT 4WD 4S HT BS6.2 | V25: TANGO RED | W25: ACTIVE
A26: AW5068ZAT2B1UC01WQ | B26: Thar | C26: LXT P MT 4WD 4S HT BS6.2 | D26: PV | E26: NON XUV | F26: PETROL | G26: 4 | H26: 4 | I26: MANUAL | J26: 4WD | K26: SUV | L26: COMPLETE | M26: 1997 | P26: 0.4 | Q26: PRIVATE | R26: YES | S26: THAR | T26: LXT P MT 4WD 4S HT BS6.2 | U26: THAR LXT P MT 4WD 4S HT BS6.2 | V26: EVEREST WHITE | W26: ACTIVE
A27: AW5068ZAT2B1UC01XJ | B27: Thar | C27: LXT P MT 4WD 4S HT BS6.2 | D27: PV | E27: NON XUV | F27: PETROL | G27: 4 | H27: 4 | I27: MANUAL | J27: 4WD | K27: SUV | L27: COMPLETE | M27: 1997 | P27: 0.4 | Q27: PRIVATE | R27: YES | S27: THAR | T27: LXT P MT 4WD 4S HT BS6.2 | U27: THAR LXT P MT 4WD 4S HT BS6.2 | V27: STEALTH BLACK | W27: ACTIVE
A28: AW5076YYT2D4MF01AH | B28: Thar Roxx | C28: AX3L DMT 2WD | D28: PV | E28: NON XUV | F28: DIESEL | G28: 5 | H28: 4 | I28: MANUAL | J28: RWD | K28: SUV | L28: COMPLETE | M28: 2184 | P28: 0.4 | Q28: PRIVATE | R28: YES | S28: THAR ROXX | T28: AX3L DMT 2WD | U28: THAR ROXX AX3L DMT 2WD | V28: DEEP FOREST | W28: ACTIVE
A29: AW5076YYT2D4MF01AJ | B29: Thar Roxx | C29: AX3L DMT 2WD | D29: PV | E29: NON XUV | F29: DIESEL | G29: 5 | H29: 4 | I29: MANUAL | J29: RWD | K29: SUV | L29: COMPLETE | M29: 2184 | P29: 0.4 | Q29: PRIVATE | R29: YES | S29: THAR ROXX | T29: AX3L DMT 2WD | U29: THAR ROXX AX3L DMT 2WD | V29: BURNT SIENNA | W29: ACTIVE
A30: 0000AMJ00390N | B30: TREO AUTO | C30: TREO 2.0 SFT OCEANIC BLUE | D30: LMM | E30: LMM | F30: ELECTRIC | G30: 4 | H30: 3 | I30: AUTOMATIC | J30: RWD | K30: PASSENGER | L30: COMPLETE | P30: 0.05 | Q30: PASSENGER | R30: NO | S30: TREO AUTO | T30: 2.0 SOFT TOP | U30: TREO AUTO 2.0 SOFT TOP | V30: OCEANIC BLUE | W30: ACTIVE
A31: 0000AMJ00650N | B31: TREO AUTO | C31: TREO 2.0 SFT ROSE PINK | D31: LMM | E31: LMM | F31: ELECTRIC | G31: 4 | H31: 3 | I31: AUTOMATIC | J31: RWD | K31: PASSENGER | L31: COMPLETE | P31: 0.05 | Q31: PASSENGER | R31: NO | S31: TREO AUTO | T31: 2.0 SOFT TOP | U31: TREO AUTO 2.0 SOFT TOP | V31: ROSE PINK | W31: ACTIVE
A32: 0000ATA00030N | B32: TREO PLUS SM | C32: TREO PLUS SFT SM BLK YEL | D32: LMM | E32: LMM | F32: ELECTRIC | G32: 4 | H32: 3 | I32: AUTOMATIC | J32: RWD | K32: PASSENGER | L32: COMPLETE | P32: 0.05 | Q32: PASSENGER | R32: NO | S32: TREO PLUS METAL | T32: SOFT TOP | U32: TREO PLUS METAL SOFT TOP | V32: BLACK YELLOW | W32: ACTIVE
A33: 0000ATA00030N | B33: TREO PLUS SM | C33: TREO PLUS SFT SM BLK YEL | D33: LMM | E33: LMM | F33: ELECTRIC | G33: 4 | H33: 3 | I33: AUTOMATIC | J33: RWD | K33: PASSENGER | L33: COMPLETE | P33: 0.05 | Q33: PASSENGER | R33: NO | S33: TREO PLUS METAL | T33: SOFT TOP | U33: TREO PLUS METAL SOFT TOP | V33: BLACK YELLOW | W33: ACTIVE
A34: 0000ATA00250N | B34: TREO PLUS SM | C34: TREO PLUS SFT SM BLK-OCEANIC BLUE | D34: LMM | E34: LMM | F34: ELECTRIC | G34: 4 | H34: 3 | I34: AUTOMATIC | J34: RWD | K34: PASSENGER | L34: COMPLETE | P34: 0.05 | Q34: PASSENGER | R34: NO | S34: TREO PLUS METAL | T34: SOFT TOP | U34: TREO PLUS METAL SOFT TOP | V34: OCEANIC BLUE | W34: ACTIVE
A35: 0000ATA00250N | B35: TREO PLUS SM | C35: TREO PLUS SFT SM BLK-OCEANIC BLUE | D35: LMM | E35: LMM | F35: ELECTRIC | G35: 4 | H35: 3 | I35: AUTOMATIC | J35: RWD | K35: PASSENGER | L35: COMPLETE | P35: 0.05 | Q35: PASSENGER | R35: NO | S35: TREO PLUS METAL | T35: SOFT TOP | U35: TREO PLUS METAL SOFT TOP | V35: OCEANIC BLUE | W35: ACTIVE
A36: 0000ATA00220N | B36: TREO PLUS SM | C36: TREO PLUS SFT SM GREEN -YEL | D36: LMM | E36: LMM | F36: ELECTRIC | G36: 4 | H36: 3 | I36: AUTOMATIC | J36: RWD | K36: PASSENGER | L36: COMPLETE | P36: 0.05 | Q36: PASSENGER | R36: NO | S36: TREO PLUS METAL | T36: SOFT TOP | U36: TREO PLUS METAL SOFT TOP | V36: GREEN YELLOW | W36: ACTIVE
A37: 0000ATA00220N | B37: TREO PLUS SM | C37: TREO PLUS SFT SM GREEN -YEL | D37: LMM | E37: LMM | F37: ELECTRIC | G37: 4 | H37: 3 | I37: AUTOMATIC | J37: RWD | K37: PASSENGER | L37: COMPLETE | P37: 0.05 | Q37: PASSENGER | R37: NO | S37: TREO PLUS METAL | T37: SOFT TOP | U37: TREO PLUS METAL SOFT TOP | V37: GREEN YELLOW | W37: ACTIVE
A38: 0000ATA00210N | B38: TREO PLUS SM | C38: TREO PLUS SFT SM-DEMO | D38: LMM | E38: LMM | F38: ELECTRIC | G38: 4 | H38: 3 | I38: AUTOMATIC | J38: RWD | K38: PASSENGER | L38: COMPLETE | P38: 0.05 | Q38: PASSENGER | R38: NO | S38: TREO PLUS METAL | T38: SOFT TOP-DEMO | U38: TREO PLUS METAL SOFT TOP-DEMO | V38: BLUE WHITE | W38: INACTIVE
A39: 0000ATA00180N | B39: TREO SM | C39: TREO HRT SM | D39: LMM | E39: LMM | F39: ELECTRIC | G39: 4 | H39: 3 | I39: AUTOMATIC | J39: RWD | K39: PASSENGER | L39: COMPLETE | P39: 0.05 | Q39: PASSENGER | R39: NO | S39: TREO METAL | T39: HARD TOP | U39: TREO METAL HARD TOP | V39: BLUE WHITE | W39: ACTIVE
A40: 0000ATA00180N | B40: TREO SM | C40: TREO HRT SM | D40: LMM | E40: LMM | F40: ELECTRIC | G40: 4 | H40: 3 | I40: AUTOMATIC | J40: RWD | K40: PASSENGER | L40: COMPLETE | P40: 0.05 | Q40: PASSENGER | R40: NO | S40: TREO METAL | T40: HARD TOP | U40: TREO METAL HARD TOP | V40: BLUE WHITE | W40: ACTIVE
A41: 0000ATA00170N | B41: TREO SM | C41: TREO SFT SM | D41: LMM | E41: LMM | F41: ELECTRIC | G41: 4 | H41: 3 | I41: AUTOMATIC | J41: RWD | K41: PASSENGER | L41: COMPLETE | P41: 0.05 | Q41: PASSENGER | R41: NO | S41: TREO METAL | T41: SOFT TOP | U41: TREO METAL SOFT TOP | V41: BLUE WHITE | W41: ACTIVE
A42: 0000ATA00170N | B42: TREO SM | C42: TREO SFT SM | D42: LMM | E42: LMM | F42: ELECTRIC | G42: 4 | H42: 3 | I42: AUTOMATIC | J42: RWD | K42: PASSENGER | L42: COMPLETE | P42: 0.05 | Q42: PASSENGER | R42: NO | S42: TREO METAL | T42: SOFT TOP | U42: TREO METAL SOFT TOP | V42: BLUE WHITE | W42: ACTIVE
A43: 0000AT300030N | B43: TREO SM | C43: TREO SFT SM | D43: LMM | E43: LMM | F43: ELECTRIC | G43: 4 | H43: 3 | I43: AUTOMATIC | J43: RWD | K43: PASSENGER | L43: COMPLETE | P43: 0.05 | Q43: PASSENGER | R43: NO | S43: TREO METAL | T43: SOFT TOP | U43: TREO METAL SOFT TOP | W43: ACTIVE
A44: 0000AT300010N | B44: TREO SM | C44: TREO SFT SM BLK-YEL | D44: LMM | E44: LMM | F44: ELECTRIC | G44: 4 | H44: 3 | I44: AUTOMATIC | J44: RWD | K44: PASSENGER | L44: COMPLETE | P44: 0.05 | Q44: PASSENGER | R44: NO | S44: TREO METAL | T44: SOFT TOP-YEL | U44: TREO METAL SOFT TOP-YEL | V44: BLACK YELLOW | W44: ACTIVE
A45: 0000AT300010N | B45: TREO SM | C45: TREO SFT SM BLK-YEL | D45: LMM | E45: LMM | F45: ELECTRIC | G45: 4 | H45: 3 | I45: AUTOMATIC | J45: RWD | K45: PASSENGER | L45: COMPLETE | P45: 0.05 | Q45: PASSENGER | R45: NO | S45: TREO METAL | T45: SOFT TOP-YEL | U45: TREO METAL SOFT TOP-YEL | V45: BLACK YELLOW | W45: ACTIVE
A46: 0000AMJ00960N | B46: TREO YAARI | C46: TREO YAARI 72AH - SFT GREEN-YELLO | D46: LMM | E46: LMM | F46: ELECTRIC | G46: 2 | H46: 3 | I46: AUTOMATIC | J46: RWD | K46: PASSENGER | L46: COMPLETE | P46: 0.05 | Q46: PASSENGER | R46: NO | S46: TREO YAARI | T46: 72AH - SOFT TOP | U46: TREO YAARI 72AH - SOFT TOP | V46: GREEN YELLOW | W46: ACTIVE
A47: 0000AMJ00040N | B47: TREO YAARI | C47: TREO YAARI HRT | D47: LMM | E47: LMM | F47: ELECTRIC | G47: 5 | H47: 3 | I47: AUTOMATIC | J47: RWD | K47: PASSENGER | L47: COMPLETE | P47: 0.05 | Q47: PASSENGER | R47: NO | S47: TREO YAARI | T47: HARD TOP | U47: TREO YAARI HARD TOP | V47: BLUE WHITE | W47: ACTIVE
A48: 0000AMJ00020N | B48: TREO YAARI | C48: TREO YAARI SFT | D48: LMM | E48: LMM | F48: ELECTRIC | G48: 5 | H48: 3 | I48: AUTOMATIC | J48: RWD | K48: PASSENGER | L48: COMPLETE | P48: 0.05 | Q48: PASSENGER | R48: NO | S48: TREO YAARI | T48: SOFT TOP | U48: TREO YAARI SOFT TOP | V48: BLUE WHITE | W48: ACTIVE
A49: 0000AMJ00020N | B49: TREO YAARI | C49: TREO YAARI SFT | D49: LMM | E49: LMM | F49: ELECTRIC | G49: 5 | H49: 3 | I49: AUTOMATIC | J49: RWD | K49: PASSENGER | L49: COMPLETE | P49: 0.05 | Q49: PASSENGER | R49: NO | S49: TREO YAARI | T49: SOFT TOP | U49: TREO YAARI SOFT TOP | V49: BLUE WHITE | W49: ACTIVE
A50: 0000AMN00120N | B50: TREO YAARI CARGO | C50: TREO YAARI CARGO HRT FB | D50: LMM | E50: LMM | F50: ELECTRIC | G50: 2 | H50: 3 | I50: AUTOMATIC | J50: RWD | K50: CARGO | L50: COMPLETE | O50: 665 | P50: 0.05 | Q50: GOODS | R50: NO | S50: TREO YAARI CARGO | T50: HARD TOP FLAT BED | U50: TREO YAARI CARGO HARD TOP FLAT BED | V50: BLUE WHITE | W50: ACTIVE
A51: 0000AMN00100N | B51: TREO YAARI CARGO | C51: TREO YAARI CARGO HRT PU | D51: LMM | E51: LMM | F51: ELECTRIC | G51: 2 | H51: 3 | I51: AUTOMATIC | J51: RWD | K51: CARGO | L51: COMPLETE | O51: 665 | P51: 0.05 | Q51: GOODS | R51: NO | S51: TREO YAARI CARGO | T51: HARD TOP PICK UP | U51: TREO YAARI CARGO HARD TOP PICK UP | V51: BLUE WHITE | W51: ACTIVE
A52: 0000AMH00040N | B52: TREO ZOR | C52: Treo Zor | D52: LMM | E52: LMM | F52: ELECTRIC | G52: 2 | H52: 3 | I52: AUTOMATIC | J52: RWD | K52: CARGO | L52: COMPLETE | O52: 995 | P52: 0.05 | Q52: GOODS | R52: NO | S52: TREO ZOR | T52: PICK UP | U52: TREO ZOR PICK UP | V52: BLUE WHITE | W52: ACTIVE
A53: 0000AMH00090N | B53: TREO ZOR | C53: TREO ZOR DV | D53: LMM | E53: LMM | F53: ELECTRIC | G53: 2 | H53: 3 | I53: AUTOMATIC | J53: RWD | K53: CARGO | L53: COMPLETE | O53: 995 | P53: 0.05 | Q53: GOODS | R53: NO | S53: TREO ZOR | T53: DELIVERY VAN | U53: TREO ZOR DELIVERY VAN | V53: BLUE WHITE | W53: ACTIVE
A54: 0000AMH00080N | B54: TREO ZOR | C54: Treo Zor FB | D54: LMM | E54: LMM | F54: ELECTRIC | G54: 2 | H54: 3 | I54: AUTOMATIC | J54: RWD | K54: CARGO | L54: COMPLETE | O54: 995 | P54: 0.05 | Q54: GOODS | R54: NO | S54: TREO ZOR | T54: FLAT BED | U54: TREO ZOR FLAT BED | V54: BLUE WHITE | W54: ACTIVE
A55: 1EP2GN4TVNUG1BG | B55: UDO | C55: UDO ST | D55: LMM | E55: LMM | F55: ELECTRIC | G55: 4 | H55: 3 | I55: AUTOMATIC | J55: RWD | K55: PASSENGER | L55: COMPLETE | P55: 0.05 | Q55: PASSENGER | R55: NO | S55: UDO | T55: SOFT TOP | U55: UDO SOFT TOP | W55: ACTIVE
A56: 1EP2GN4TVNUG1OB | B56: UDO | C56: UDO ST | D56: LMM | E56: LMM | F56: ELECTRIC | G56: 4 | H56: 3 | I56: AUTOMATIC | J56: RWD | K56: PASSENGER | L56: COMPLETE | P56: 0.05 | Q56: PASSENGER | R56: NO | S56: UDO | T56: SOFT TOP | U56: UDO SOFT TOP | V56: OCEANIC BLUE | W56: ACTIVE
A57: G2D4AACVXB3F1B01WT | B57: VEERO | C57: 1.6XXL SD V2 - Airbag | D57: CV | E57: CV | F57: DIESEL | G57: 3 | H57: 4 | I57: MANUAL | J57: RWD | K57: CARGO | L57: COMPLETE | O57: 3170 | P57: 0.18 | Q57: GOODS | R57: NO | S57: VEERO | T57: 1.6XXL SD V2 - AIRBAG | U57: VEERO 1.6XXL SD V2 - AIRBAG | V57: POLAR WHITE | W57: ACTIVE
A58: G2G4AACUXB3F1B01WT | B58: VEERO | C58: 1.6XXL SD V4 | D58: CV | E58: CV | F58: DIESEL | G58: 3 | H58: 4 | I58: MANUAL | J58: RWD | K58: CARGO | L58: COMPLETE | O58: 3170 | P58: 0.18 | Q58: GOODS | R58: NO | S58: VEERO | T58: 1.6XXL SD V4 | U58: VEERO 1.6XXL SD V4 | V58: POLAR WHITE | W58: ACTIVE
A59: G2F4AACUXB3F1B01QT | B59: VEERO | C59: 1.6XXL SD V6 | D59: CV | E59: CV | F59: DIESEL | G59: 3 | H59: 4 | I59: MANUAL | J59: RWD | K59: CARGO | L59: COMPLETE | O59: 3170 | P59: 0.18 | Q59: GOODS | R59: NO | S59: VEERO | T59: 1.6XXL SD V6 | U59: VEERO 1.6XXL SD V6 | V59: CONCRETE GREY | W59: ACTIVE
A60: G2F4AACUXB3F1B01WT | B60: VEERO | C60: 1.6XXL SD V6 | D60: CV | E60: CV | F60: DIESEL | G60: 3 | H60: 4 | I60: MANUAL | J60: RWD | K60: CARGO | L60: COMPLETE | O60: 3170 | P60: 0.18 | Q60: GOODS | R60: NO | S60: VEERO | T60: 1.6XXL SD V6 | U60: VEERO 1.6XXL SD V6 | V60: POLAR WHITE | W60: ACTIVE
A61: BM32AA515MB01D00RQ | B61: XEV9E | C61: XEV 9e One B59 R19 C11 | D61: BEV | E61: BEV | F61: ELECTRIC | G61: 5 | H61: 4 | I61: AUTOMATIC | J61: RWD | K61: SUV | L61: COMPLETE | N61: >65KW | P61: 0.05 | Q61: PRIVATE | R61: NO | S61: XEV9E | T61: ONE B59 R19 C11 | U61: XEV9E ONE B59 R19 C11 | V61: TANGO RED | W61: ACTIVE | X61: Pack 1
A62: BM32AA515MB01D00XJ | B62: XEV9E | C62: XEV 9e One B59 R19 C11 | D62: BEV | E62: BEV | F62: ELECTRIC | G62: 5 | H62: 4 | I62: AUTOMATIC | J62: RWD | K62: SUV | L62: COMPLETE | N62: >65KW | P62: 0.05 | Q62: PRIVATE | R62: NO | S62: XEV9E | T62: ONE B59 R19 C11 | U62: XEV9E ONE B59 R19 C11 | V62: STEALTH BLACK | W62: ACTIVE | X62: Pack 1
A63: BW62AB717MC01D02XJ | B63: XEV9S | C63: XEV 9S TWO ABOVE B79 R18 7STR NCH | D63: BEV | E63: BEV | F63: ELECTRIC | G63: 7 | H63: 4 | I63: AUTOMATIC | J63: RWD | K63: SUV | L63: COMPLETE | N63: >65KW | P63: 0.05 | Q63: PRIVATE | R63: NO | S63: XEV9S | T63: TWO ABOVE B79 R18 7STR NCH | U63: XEV9S TWO ABOVE B79 R18 7STR NCH | V63: STEALTH BLACK | W63: ACTIVE | X63: Pack 2
A64: BW62AB717MC01D02WQ | B64: XEV9S | C64: XEV 9S TWO ABOVE B79 R18 7STR NCH | D64: BEV | E64: BEV | F64: ELECTRIC | G64: 7 | H64: 4 | I64: AUTOMATIC | J64: RWD | K64: SUV | L64: COMPLETE | N64: >65KW | P64: 0.05 | Q64: PRIVATE | R64: NO | S64: XEV9S | T64: TWO ABOVE B79 R18 7STR NCH | U64: XEV9S TWO ABOVE B79 R18 7STR NCH | W64: ACTIVE | X64: Pack 2
A65: BW62AB717MC01D02BN | B65: XEV9S | C65: XEV 9S TWO ABOVE B79 R18 7STR NCH | D65: BEV | E65: BEV | F65: ELECTRIC | G65: 7 | H65: 4 | I65: AUTOMATIC | J65: RWD | K65: SUV | L65: COMPLETE | N65: >65KW | P65: 0.05 | Q65: PRIVATE | R65: NO | S65: XEV9S | T65: TWO ABOVE B79 R18 7STR NCH | U65: XEV9S TWO ABOVE B79 R18 7STR NCH | W65: ACTIVE | X65: Pack 2
A66: AS22JPEW5T403C00QK | B66: XUV 3XO | C66: AX5 DS AS | D66: PV | E66: XUV | F66: DIESEL | G66: 5 | H66: 4 | I66: AUTOMATIC | J66: FWD | K66: COMPACT SUV | L66: COMPLETE | M66: 1498 | P66: 0.18 | Q66: PRIVATE | R66: YES | S66: XUV 3XO | T66: AX5 DS AS | U66: XUV 3XO AX5 DS AS | V66: GALAXY GREY | W66: ACTIVE
A67: AS22JPEW5T403C00WQ | B67: XUV 3XO | C67: AX5 DS AS | D67: PV | E67: XUV | F67: DIESEL | G67: 5 | H67: 4 | I67: AUTOMATIC | J67: FWD | K67: COMPACT SUV | L67: COMPLETE | M67: 1498 | P67: 0.18 | Q67: PRIVATE | R67: YES | S67: XUV 3XO | T67: AX5 DS AS | U67: XUV 3XO AX5 DS AS | V67: EVEREST WHITE | W67: ACTIVE
A68: AS22JPEW5T403C00XJ | B68: XUV 3XO | C68: AX5 DS AS | D68: PV | E68: XUV | F68: DIESEL | G68: 5 | H68: 4 | I68: AUTOMATIC | J68: FWD | K68: COMPACT SUV | L68: COMPLETE | M68: 1498 | P68: 0.18 | Q68: PRIVATE | R68: YES | S68: XUV 3XO | T68: AX5 DS AS | U68: XUV 3XO AX5 DS AS | V68: STEALTH BLACK | W68: ACTIVE
A69: AS22PC215MB09E00RQ | B69: XUV3XO EV | C69: AX7L FH | D69: PV | E69: XUV | F69: ELECTRIC | G69: 5 | H69: 4 | I69: AUTOMATIC | J69: FWD | K69: COMPACT SUV | L69: COMPLETE | N69: >65KW | P69: 0.05 | Q69: PRIVATE | R69: YES | S69: XUV3XO EV | T69: AX7L FH | U69: XUV3XO EV AX7L FH | V69: TANGO RED | W69: ACTIVE
A70: AS22PC215MB09E00WQ | B70: XUV3XO EV | C70: AX7L FH | D70: PV | E70: XUV | F70: ELECTRIC | G70: 5 | H70: 4 | I70: AUTOMATIC | J70: FWD | K70: COMPACT SUV | L70: COMPLETE | N70: >65KW | P70: 0.05 | Q70: PRIVATE | R70: YES | S70: XUV3XO EV | T70: AX7L FH | U70: XUV3XO EV AX7L FH | V70: EVEREST WHITE | W70: ACTIVE
A71: AS22PC215MB09E00XJ | B71: XUV3XO EV | C71: AX7L FH | D71: PV | E71: XUV | F71: ELECTRIC | G71: 5 | H71: 4 | I71: AUTOMATIC | J71: FWD | K71: COMPACT SUV | L71: COMPLETE | N71: >65KW | P71: 0.05 | Q71: PRIVATE | R71: YES | S71: XUV3XO EV | T71: AX7L FH | U71: XUV3XO EV AX7L FH | V71: STEALTH BLACK | W71: ACTIVE
A72: AS22AA215MA08A00WQ | B72: XUV400 | C72: EC PRO - Battery 34.5 Kwh - Charger 3.2 Kw - E | D72: PV | E72: XUV | F72: ELECTRIC | G72: 5 | H72: 4 | I72: AUTOMATIC | J72: FWD | K72: COMPACT SUV | L72: COMPLETE | N72: >65KW | P72: 0.05 | Q72: PRIVATE | R72: YES | S72: XUV400 | T72: EC PRO - BATTERY 34.5 KWH - CHARGER 3.2 KW - E | U72: XUV400 EC PRO - BATTERY 34.5 KWH - CHARGER 3.2 KW - E | V72: EVEREST WHITE | W72: ACTIVE
A73: AS22AA215MA08A00QK | B73: XUV400 | C73: EC PRO - Battery 34.5 Kwh - Charger 3.2 Kw - E | D73: PV | E73: XUV | F73: ELECTRIC | G73: 5 | H73: 4 | I73: AUTOMATIC | J73: FWD | K73: COMPACT SUV | L73: COMPLETE | N73: >65KW | P73: 0.05 | Q73: PRIVATE | R73: YES | S73: XUV400 | T73: EC PRO - BATTERY 34.5 KWH - CHARGER 3.2 KW - E | U73: XUV400 EC PRO - BATTERY 34.5 KWH - CHARGER 3.2 KW - E | V73: GALAXY GREY | W73: ACTIVE
A74: AW62BFZE7TA10A00WQ | B74: XUV700 | C74: MX PET MT 7 STR - E BS6.2 - New | D74: PV | E74: XUV | F74: PETROL | G74: 7 | H74: 4 | I74: MANUAL | J74: FWD | K74: SUV | L74: COMPLETE | M74: 1999 | P74: 0.4 | Q74: PRIVATE | R74: YES | S74: XUV700 | T74: MX PET MT 7 STR - E BS6.2 - NEW | U74: XUV700 MX PET MT 7 STR - E BS6.2 - NEW | V74: EVEREST WHITE | W74: ACTIVE
A75: AW62BFZE7TA10A00XJ | B75: XUV700 | C75: MX PET MT 7 STR - E BS6.2 - New | D75: PV | E75: XUV | F75: PETROL | G75: 7 | H75: 4 | I75: MANUAL | J75: FWD | K75: SUV | L75: COMPLETE | M75: 1999 | P75: 0.4 | Q75: PRIVATE | R75: YES | S75: XUV700 | T75: MX PET MT 7 STR - E BS6.2 - NEW | U75: XUV700 MX PET MT 7 STR - E BS6.2 - NEW | V75: STEALTH BLACK | W75: ACTIVE
A76: AW62BFZE7TA08A00SF | B76: XUV700 | C76: MX PET MT 7 STR - E BS6.2 - New | D76: PV | E76: XUV | F76: PETROL | G76: 7 | H76: 4 | I76: MANUAL | J76: FWD | K76: SUV | L76: COMPLETE | M76: 1999 | P76: 0.4 | Q76: PRIVATE | R76: YES | S76: XUV700 | T76: MX PET MT 7 STR - E BS6.2 - NEW | U76: XUV700 MX PET MT 7 STR - E BS6.2 - NEW | V76: DAZZLING SILVER | W76: ACTIVE
A77: AW62BFZE7TA08A00XH | B77: XUV700 | C77: MX PET MT 7 STR - E BS6.2 - New | D77: PV | E77: XUV | F77: PETROL | G77: 7 | H77: 4 | I77: MANUAL | J77: FWD | K77: SUV | L77: COMPLETE | M77: 1999 | P77: 0.4 | Q77: PRIVATE | R77: YES | S77: XUV700 | T77: MX PET MT 7 STR - E BS6.2 - NEW | U77: XUV700 MX PET MT 7 STR - E BS6.2 - NEW | V77: NAPOLI BLACK | W77: ACTIVE
A78: AW62BFZE7TA08A00JD | B78: XUV700 | C78: MX PET MT 7 STR - E BS6.2 - New | D78: PV | E78: XUV | F78: PETROL | G78: 7 | H78: 4 | I78: MANUAL | J78: FWD | K78: SUV | L78: COMPLETE | M78: 1999 | P78: 0.4 | Q78: PRIVATE | R78: YES | S78: XUV700 | T78: MX PET MT 7 STR - E BS6.2 - NEW | U78: XUV700 MX PET MT 7 STR - E BS6.2 - NEW | V78: DEEP FOREST | W78: ACTIVE
A79: AW62BXZS7TA11D00BN | B79: XUV7XO | C79: AX DSL MT 7 STR | D79: PV | E79: XUV | F79: DIESEL | G79: 7 | H79: 4 | I79: MANUAL | J79: FWD | K79: SUV | L79: COMPLETE | M79: 2184 | P79: 0.4 | Q79: PRIVATE | R79: YES | S79: XUV7XO | T79: AX DSL MT 7 STR | U79: XUV7XO AX DSL MT 7 STR | V79: NEBULA BLUE | W79: ACTIVE
A80: AW62BXZS7TA11D00BZ | B80: XUV7XO | C80: AX DSL MT 7 STR | D80: PV | E80: XUV | F80: DIESEL | G80: 7 | H80: 4 | I80: MANUAL | J80: FWD | K80: SUV | L80: COMPLETE | M80: 2184 | P80: 0.4 | Q80: PRIVATE | R80: YES | S80: XUV7XO | T80: AX DSL MT 7 STR | U80: XUV7XO AX DSL MT 7 STR | V80: MIDNIGHT BLACK | W80: ACTIVE
A81: AW62BXZS7TA11D00QW | B81: XUV7XO | C81: AX DSL MT 7 STR | D81: PV | E81: XUV | F81: DIESEL | G81: 7 | H81: 4 | I81: MANUAL | J81: FWD | K81: SUV | L81: COMPLETE | M81: 2184 | P81: 0.4 | Q81: PRIVATE | R81: YES | S81: XUV7XO | T81: AX DSL MT 7 STR | U81: XUV7XO AX DSL MT 7 STR | V81: GALAXY GREY | W81: ACTIVE
A82: AW62BXZS7TA11D00WQ | B82: XUV7XO | C82: AX DSL MT 7 STR | D82: PV | E82: XUV | F82: DIESEL | G82: 7 | H82: 4 | I82: MANUAL | J82: FWD | K82: SUV | L82: COMPLETE | M82: 2184 | P82: 0.4 | Q82: PRIVATE | R82: YES | S82: XUV7XO | T82: AX DSL MT 7 STR | U82: XUV7XO AX DSL MT 7 STR | V82: EVEREST WHITE | W82: ACTIVE
A83: AW62BXZS7TA11D00XJ | B83: XUV7XO | C83: AX DSL MT 7 STR | D83: PV | E83: XUV | F83: DIESEL | G83: 7 | H83: 4 | I83: MANUAL | J83: FWD | K83: SUV | L83: COMPLETE | M83: 2184 | P83: 0.4 | Q83: PRIVATE | R83: YES | S83: XUV7XO | T83: AX DSL MT 7 STR | U83: XUV7XO AX DSL MT 7 STR | V83: STEALTH BLACK | W83: ACTIVE
A84: AP61WLED2BB18J00WD | B84: ZEO | C84: MAHINDRA ZEO V2 DV 200 | D84: LMM | E84: LMM | F84: ELECTRIC | G84: 2 | H84: 4 | I84: AUTOMATIC | J84: RWD | K84: CARGO | L84: COMPLETE | O84: 1675 | P84: 0.05 | Q84: GOODS | R84: NO | S84: ZEO | T84: V2 DELIVERY VAN 200 | U84: ZEO V2 DELIVERY VAN 200 | V84: WHITE | W84: ACTIVE
A85: AP61WLED2BB18J99WD | B85: ZEO | C85: MAHINDRA ZEO V2 DV 200-DEMO | D85: LMM | E85: LMM | F85: ELECTRIC | G85: 2 | H85: 4 | I85: AUTOMATIC | J85: RWD | K85: CARGO | L85: COMPLETE | O85: 1675 | P85: 0.05 | Q85: GOODS | R85: NO | S85: ZEO | T85: V2 DELIVERY VAN 200-DEMO | U85: ZEO V2 DELIVERY VAN 200-DEMO | V85: WHITE | W85: INACTIVE
A86: AP61WLED2BB18A99WD | B86: ZEO | C86: MAHINDRA ZEO V2-DEMO | D86: LMM | E86: LMM | F86: ELECTRIC | G86: 2 | H86: 4 | I86: AUTOMATIC | J86: RWD | K86: CARGO | L86: COMPLETE | O86: 1675 | P86: 0.05 | Q86: GOODS | R86: NO | S86: ZEO | T86: V2-DEMO | U86: ZEO V2-DEMO | V86: WHITE | W86: INACTIVE
A87: 1EV2DD1TUFVB1WD | B87: ZOR GRAND | C87: ZOR GRAND DV | D87: LMM | E87: LMM | F87: ELECTRIC | G87: 1 | H87: 3 | I87: AUTOMATIC | J87: RWD | K87: CARGO | L87: COMPLETE | O87: 998 | P87: 0.05 | Q87: GOODS | R87: NO | S87: ZOR GRAND | T87: DELIVERY VAN | U87: ZOR GRAND DELIVERY VAN | V87: WHITE | W87: ACTIVE
A88: 1EV2DD1TUFWB1WD | B88: ZOR GRAND | C88: ZOR GRAND DV + | D88: LMM | E88: LMM | F88: ELECTRIC | G88: 1 | H88: 3 | I88: AUTOMATIC | J88: RWD | K88: CARGO | L88: COMPLETE | O88: 998 | P88: 0.05 | Q88: GOODS | R88: NO | S88: ZOR GRAND | T88: DELIVERY VAN + | U88: ZOR GRAND DELIVERY VAN + | V88: WHITE | W88: ACTIVE
A89: 1EV2ZE1TUFYB1WD | B89: ZOR GRAND R | C89: ZOR GRAND FB R | D89: LMM | E89: LMM | F89: ELECTRIC | G89: 1 | H89: 3 | I89: AUTOMATIC | J89: RWD | K89: CARGO | L89: COMPLETE | O89: 998 | P89: 0.05 | Q89: GOODS | R89: NO | S89: ZOR GRAND R | T89: FLAT BED | U89: ZOR GRAND R FLAT BED | V89: WHITE | W89: ACTIVE
A90: 1EV2ZE1TUFLB1WD | B90: ZOR GRAND R | C90: ZOR GRAND PU R | D90: LMM | E90: LMM | F90: ELECTRIC | G90: 1 | H90: 3 | I90: AUTOMATIC | J90: RWD | K90: CARGO | L90: COMPLETE | O90: 998 | P90: 0.05 | Q90: GOODS | R90: NO | S90: ZOR GRAND R | T90: PICK UP | U90: ZOR GRAND R PICK UP | V90: WHITE | W90: ACTIVE
A91: 1EV2DD1TUFWB1OB | B91: ZOR GRAND RE | C91: ZOR GRAND DV + RE | D91: LMM | E91: LMM | F91: ELECTRIC | G91: 1 | H91: 3 | I91: AUTOMATIC | J91: RWD | K91: CARGO | L91: COMPLETE | O91: 998 | P91: 0.05 | Q91: GOODS | R91: NO | S91: ZOR GRAND RE | T91: DELIVERY VAN + | U91: ZOR GRAND RE DELIVERY VAN + | V91: OCEANIC BLUE | W91: ACTIVE
A92: 1EV2DD1TUFVB1OB | B92: ZOR GRAND RE | C92: ZOR GRAND DV RE | D92: LMM | E92: LMM | F92: ELECTRIC | G92: 1 | H92: 3 | I92: AUTOMATIC | J92: RWD | K92: CARGO | L92: COMPLETE | O92: 998 | P92: 0.05 | Q92: GOODS | R92: NO | S92: ZOR GRAND RE | T92: DELIVERY VAN | U92: ZOR GRAND RE DELIVERY VAN | V92: OCEANIC BLUE | W92: ACTIVE

Sheet PV Vehicle
A1: Model Code | B1: OEM Model | C1: OEM Variant | D1: Colour Name | E1: Transmission | F1: Seating | G1: Status
A2: SSS24MJA7R8E7XJ | B2: Scorpio | C2: Classic S11 BS6.2 - E | D2: STEALTH BLACK | E2: MT | F2: 7 | G2: Live
A3: SSS24MJA7R8E6XJ | B3: Scorpio | C3: Classic S11 BS6.2 - E | D3: STEALTH BLACK | E3: MT | F3: 7 | G3: Live
A4: AW5026JWT7D4KF01AL | B4: Thar Roxx | C4: AX7 PAT 2WD - Star Edition | D4: TANGO RED | E4: AT | F4: 5 | G4: Live
A5: AW5026JWT7D4KF01AM | B5: Thar Roxx | C5: AX7 PAT 2WD - Star Edition | D5: STEALTH BLACK | E5: AT | F5: 5 | G5: Live
A6: AW5026JWT7D4KF01AV | B6: Thar Roxx | C6: AX7 PAT 2WD - Star Edition | D6: CITRINE YELLOW | E6: AT | F6: 5 | G6: Live
A7: AW5026JWT7D4KF01ZP | B7: Thar Roxx | C7: AX7 PAT 2WD - Star Edition | D7: EVEREST WHITE | E7: AT | F7: 5 | G7: Live
A8: AW5026KYT7D4KF01AL | B8: Thar Roxx | C8: AX7 DAT 2WD - Star Edition | D8: TANGO RED | E8: AT | F8: 5 | G8: Live
A9: AW5026KYT7D4KF01AM | B9: Thar Roxx | C9: AX7 DAT 2WD - Star Edition | D9: STEALTH BLACK | E9: AT | F9: 5 | G9: Live
A10: AS22SB215MB08A00CE | B10: XUV400 | C10: EL PRO FC - Battery 39.4 Kwh - Charger 7.2 Kw - E | D10: ARCTIC BLUE | E10: AT | F10: 5 | G10: Live
A11: AS22SB215MB08A00QK | B11: XUV400 | C11: EL PRO FC - Battery 39.4 Kwh - Charger 7.2 Kw - E | D11: GALAXY GREY | E11: AT | F11: 5 | G11: Live
A12: AS22SB215MB08A00RP | B12: XUV400 | C12: EL PRO FC - Battery 39.4 Kwh - Charger 7.2 Kw - E | D12: NEBULA BLUE | E12: AT | F12: 5 | G12: Live
A13: AS22SB215MB08A00WQ | B13: XUV400 | C13: EL PRO FC - Battery 39.4 Kwh - Charger 7.2 Kw - E | D13: EVEREST WHITE | E13: AT | F13: 5 | G13: Live
... A243: AW5076KYT7D4PE01XJ | B243: Thar Roxx | C243: AX7L DAT 2WD - Mocha Interiors | D243: STEALTH BLACK | E243: AT | F243: 5 | G243: Live

Sheet CV Vehicle
A1: Model Code | B1: OEM Model | C1: OEM Variant | D1: Colour Name | E1: Seating | F1: Status
A2: PKN2ADCVBS6PSND5BP | B2: PICKUP | C2: BOL CAMPER 2WD POWER STEERING BS6.2 - CV | D2: WHITE | E2: 5 | F2: Live
A3: G2C4AACVXB3F1A01QT | B3: VEERO | C3: 1.5XXL SD V2 | D3: CONCRETE GREY | E3: 3 | F3: Live
A4: G2C4AACVXB3F1A01WT | B4: VEERO | C4: 1.5XXL SD V2 | D4: POLAR WHITE | E4: 3 | F4: Live
A5: PKN2ADC2BS6PSNC5WD | B5: PICKUP | C5: BOL CAMPER GOLD RXD BS6.2 CV - Refresh | D5: WHITE | E5: 5 | F5: Live
A6: PKN2ADCVBS6PSNC5WD | B6: PICKUP | C6: BOL CAMPER 2WD BS6.2 - CV - Refresh | D6: WHITE | E6: 5 | F6: Live
A7: AAR2KSPX2TW0GWD | B7: SUPRO | C7: Supro Minitruck Excel CNG DUO BS6.2 - Tipper / Hopper | D7: DIAMOND WHITE | E7: 2 | F7: Live
A8: PKN2ADCWBS6PSND5RX | B8: PICKUP | C8: BOL CAMPER GOLD ZX 2WD BS6.2 - NEW | D8: HIGHWAY RED | E8: 5 | F8: Live
A9: PJN2CSCJBS6MSCC2WD | B9: PICKUP | C9: BOL PIK UP CBC 1.3T - BS6.2 - MS - Refresh | D9: WHITE | E9: 2 | F9: Live
A10: PJN2CSCJBS6MSFC2WD | B10: PICKUP | C10: BOL PIK UP FB 1.3T - BS6.2 - MS -Refresh | D10: WHITE | E10: 2 | F10: Live
A11: PJN2CSCJBS6PSFC2WD | B11: PICKUP | C11: BOL PIK UP FB 1.3T - BS6.2 - PS - Refresh | D11: WHITE | E11: 2 | F11: Live
A12: PJN2CSCMBS6PSFC2WD | B12: PICKUP | C12: BOL PIK UP FB 1.3T - BS6.2 - PS AC - Refresh | D12: WHITE | E12: 2 | F12: Live
A13: PJN4ASCMBS6PSNC2WD | B13: PICKUP | C13: BOL PIK UP 4WD BS6.2 - PS AC - Refresh | D13: WHITE | E13: 2 | F13: Live
... A155: PKN4ASCNBS6PSNC2WD | B155: PICKUP | C155: BOL PIK UP 4WD BS6.2 - PS - Refresh | D155: WHITE | E155: 3 | F155: Live

Sheet Price List PV
L1: Current VIN | W1: Old VIN
A2: Model Code | B2: OEM Model | C2: OEM Variant | D2: Asse Value with Freight | E2: GST | F2: GST Amount | G2: MM Inv Amt | H2: Dealer Margin | I2: Dealer Handling | J2: GST Amount 1 | K2: Ex-Showroom Price ORG | L2: OEM Scheme @ BNDP | M2: OEM Scheme with GST | N2: Dealer Cont @ BNDP | O2: Dealer Contribution with GST | P2: Total Consumer Scheme with GST (OEM + Dealer) | Q2: Cash Discount | R2: Accessories Discount | S2: Shield Discount | T2: Check | U2: Acc Dsc Elg | V2: Sheld Disc Elg | W2: OEM Scheme @ BNDP | X2: OEM Scheme with GST | Y2: Dealer Cont @ BNDP | Z2: Dealer Contribution with GST | AA2: Total Consumer Scheme with GST (OEM + Dealer) | AB2: Cash Discount | AC2: Accessories Discount | AD2: Shield Discount | AE2: Check | AF2: Acc Dsc Elg | AG2: Sheld Disc Elg
A3: AZ1116YGTTA4EA01BZ | B3: Scorpio-N | C3: Z8 L D AT 2WD 7 STR BS6.2 - N - ADAS | D3: 1557827 | E3: 40 | F3: 623131 | G3: 2180958 | H3: 68245 | I3: 0 | J3: 27298 | K3: 2276500 | L3: 53571 | M3: 75000 | N3: 17857 | O3: 25000 | P3: 100000 | Q3: 70000 | R3: 30000 | S3: 0 | T3: 0 | U3: 0.7 | V3: 1 | W3: 0 | X3: 0 | Y3: 0 | Z3: 0 | AA3: 0 | AB3: 0 | AC3: 0 | AD3: 0 | AE3: 0 | AF3: 0.7 | AG3: 1
A4: AZ1116YGTTA4EA01WQ | B4: Scorpio-N | C4: Z8 L D AT 2WD 7 STR BS6.2 - N - ADAS | D4: 1557827 | E4: 40 | F4: 623131 | G4: 2180958 | H4: 68245 | I4: 0 | J4: 27298 | K4: 2276500 | L4: 53571 | M4: 75000 | N4: 17857 | O4: 25000 | P4: 100000 | Q4: 70000 | R4: 30000 | S4: 0 | T4: 0 | U4: 0.7 | V4: 1 | W4: 0 | X4: 0 | Y4: 0 | Z4: 0 | AA4: 0 | AB4: 0 | AC4: 0 | AD4: 0 | AE4: 0 | AF4: 0.7 | AG4: 1
A5: AZ1116YGTTA4EA01SG | B5: Scorpio-N | C5: Z8 L D AT 2WD 7 STR BS6.2 - N - ADAS | D5: 1557827 | E5: 40 | F5: 623131 | G5: 2180958 | H5: 68245 | I5: 0 | J5: 27298 | K5: 2276500 | L5: 53571 | M5: 75000 | N5: 17857 | O5: 25000 | P5: 100000 | Q5: 70000 | R5: 30000 | S5: 0 | T5: 0 | U5: 0.7 | V5: 1 | W5: 0 | X5: 0 | Y5: 0 | Z5: 0 | AA5: 0 | AB5: 0 | AC5: 0 | AD5: 0 | AE5: 0 | AF5: 0.7 | AG5: 1
A6: AZ1116YGTTA4EA01JD | B6: Scorpio-N | C6: Z8 L D AT 2WD 7 STR BS6.2 - N - ADAS | D6: 1557827 | E6: 40 | F6: 623131 | G6: 2180958 | H6: 68245 | I6: 0 | J6: 27298 | K6: 2276500 | L6: 53571 | M6: 75000 | N6: 17857 | O6: 25000 | P6: 100000 | Q6: 70000 | R6: 30000 | S6: 0 | T6: 0 | U6: 0.7 | V6: 1 | W6: 0 | X6: 0 | Y6: 0 | Z6: 0 | AA6: 0 | AB6: 0 | AC6: 0 | AD6: 0 | AE6: 0 | AF6: 0.7 | AG6: 1
A7: AZ1116YGTTA4EA01XJ | B7: Scorpio-N | C7: Z8 L D AT 2WD 7 STR BS6.2 - N - ADAS | D7: 1557827 | E7: 40 | F7: 623131 | G7: 2180958 | H7: 68245 | I7: 0 | J7: 27298 | K7: 2276500 | L7: 53571 | M7: 75000 | N7: 17857 | O7: 25000 | P7: 100000 | Q7: 70000 | R7: 30000 | S7: 0 | T7: 0 | U7: 0.7 | V7: 1 | W7: 0 | X7: 0 | Y7: 0 | Z7: 0 | AA7: 0 | AB7: 0 | AC7: 0 | AD7: 0 | AE7: 0 | AF7: 0.7 | AG7: 1
A8: AZ1116YGTTA2EA01BZ | B8: Scorpio-N | C8: Z8 L D AT 2WD 6 STR BS6.2 - N - ADAS | D8: 1572843 | E8: 40 | F8: 629137 | G8: 2201980 | H8: 68943 | I8: 0 | J8: 27577 | K8: 2298500 | L8: 53571 | M8: 75000 | N8: 17857 | O8: 25000 | P8: 100000 | Q8: 70000 | R8: 30000 | S8: 0 | T8: 0 | U8: 0.7 | V8: 1 | W8: 0 | X8: 0 | Y8: 0 | Z8: 0 | AA8: 0 | AB8: 0 | AC8: 0 | AD8: 0 | AE8: 0 | AF8: 0.7 | AG8: 1
A9: AZ1116YGTTA2EA01WQ | B9: Scorpio-N | C9: Z8 L D AT 2WD 6 STR BS6.2 - N - ADAS | D9: 1572843 | E9: 40 | F9: 629137 | G9: 2201980 | H9: 68943 | I9: 0 | J9: 27577 | K9: 2298500 | L9: 53571 | M9: 75000 | N9: 17857 | O9: 25000 | P9: 100000 | Q9: 70000 | R9: 30000 | S9: 0 | T9: 0 | U9: 0.7 | V9: 1 | W9: 0 | X9: 0 | Y9: 0 | Z9: 0 | AA9: 0 | AB9: 0 | AC9: 0 | AD9: 0 | AE9: 0 | AF9: 0.7 | AG9: 1
A10: AZ1116YGTTA2EA01SG | B10: Scorpio-N | C10: Z8 L D AT 2WD 6 STR BS6.2 - N - ADAS | D10: 1572843 | E10: 40 | F10: 629137 | G10: 2201980 | H10: 68943 | I10: 0 | J10: 27577 | K10: 2298500 | L10: 53571 | M10: 75000 | N10: 17857 | O10: 25000 | P10: 100000 | Q10: 70000 | R10: 30000 | S10: 0 | T10: 0 | U10: 0.7 | V10: 1 | W10: 0 | X10: 0 | Y10: 0 | Z10: 0 | AA10: 0 | AB10: 0 | AC10: 0 | AD10: 0 | AE10: 0 | AF10: 0.7 | AG10: 1
A11: AZ1116YGTTA2EA01JD | B11: Scorpio-N | C11: Z8 L D AT 2WD 6 STR BS6.2 - N - ADAS | D11: 1572843 | E11: 40 | F11: 629137 | G11: 2201980 | H11: 68943 | I11: 0 | J11: 27577 | K11: 2298500 | L11: 53571 | M11: 75000 | N11: 17857 | O11: 25000 | P11: 100000 | Q11: 70000 | R11: 30000 | S11: 0 | T11: 0 | U11: 0.7 | V11: 1 | W11: 0 | X11: 0 | Y11: 0 | Z11: 0 | AA11: 0 | AB11: 0 | AC11: 0 | AD11: 0 | AE11: 0 | AF11: 0.7 | AG11: 1
A12: AZ1116YGTTA2EA01XJ | B12: Scorpio-N | C12: Z8 L D AT 2WD 6 STR BS6.2 - N - ADAS | D12: 1572843 | E12: 40 | F12: 629137 | G12: 2201980 | H12: 68943 | I12: 0 | J12: 27577 | K12: 2298500 | L12: 53571 | M12: 75000 | N12: 17857 | O12: 25000 | P12: 100000 | Q12: 70000 | R12: 30000 | S12: 0 | T12: 0 | U12: 0.7 | V12: 1 | W12: 0 | X12: 0 | Y12: 0 | Z12: 0 | AA12: 0 | AB12: 0 | AC12: 0 | AD12: 0 | AE12: 0 | AF12: 0.7 | AG12: 1
A13: AZ1118YGTTA4EA01BZ | B13: Scorpio-N | C13: Z8 L D AT 4WD 7 STR BS6.2 - N - ADAS | D13: 1707343 | E13: 40 | F13: 682937 | G13: 2390281 | H13: 74800 | I13: 0 | J13: 29920 | K13: 2495000 | L13: 89286 | M13: 125000 | N13: 17857 | O13: 25000 | P13: 150000 | Q13: 120000 | R13: 30000 | S13: 0 | T13: 0 | U13: 0.7 | V13: 1 | W13: 0 | X13: 0 | Y13: 0 | Z13: 0 | AA13: 0 | AB13: 0 | AC13: 0 | AD13: 0 | AE13: 0 | AF13: 0.7 | AG13: 1
A14: AZ1118YGTTA4EA01WQ | B14: Scorpio-N | C14: Z8 L D AT 4WD 7 STR BS6.2 - N - ADAS | D14: 1707343 | E14: 40 | F14: 682937 | G14: 2390281 | H14: 74800 | I14: 0 | J14: 29920 | K14: 2495000 | L14: 89286 | M14: 125000 | N14: 17857 | O14: 25000 | P14: 150000 | Q14: 120000 | R14: 30000 | S14: 0 | T14: 0 | U14: 0.7 | V14: 1 | W14: 0 | X14: 0 | Y14: 0 | Z14: 0 | AA14: 0 | AB14: 0 | AC14: 0 | AD14: 0 | AE14: 0 | AF14: 0.7 | AG14: 1
... A18: AW5068YLTTB1UC01QL | B18: Thar | C18: LXT D AT 4WD 4S HT BS6.2 | D18: 1211983 | E18: 40 | F18: 484793 | G18: 1696777 | H18: 73374 | I18: 0 | J18: 29350 | K18: 1799501 | L18: 14286 | M18: 20000 | N18: 0 | O18: 0 | P18: 20000 | Q18: 10000 | R18: 10000 | S18: 0 | T18: 0 | U18: 0.7 | V18: 1 | W18: 0 | X18: 0 | Y18: 0 | Z18: 0 | AA18: 0 | AB18: 0 | AC18: 0 | AD18: 0 | AE18: 0 | AF18: 0.7 | AG18: 1

Sheet Price List CV
L1: Current VIN | W1: Old VIN
A2: Model Code | B2: OEM Model | C2: OEM Variant | D2: Asse Value with Freight | E2: GST | F2: GST Amount | G2: MM Inv Amt | H2: Dealer Margin | I2: Dealer Handling | J2: GST Amount 1 | K2: Ex-Showroom Price ORG | L2: OEM Scheme @ BNDP | M2: OEM Scheme with GST | N2: Dealer Cont @ BNDP | O2: Dealer Contribution with GST | P2: Total Consumer Scheme with GST (OEM + Dealer) | Q2: Cash Discount | R2: Accessories Discount | S2: Shield Discount | T2: Check | U2: Acc Dsc Elg | V2: Sheld Disc Elg | W2: OEM Scheme @ BNDP | X2: OEM Scheme with GST | Y2: Dealer Cont @ BNDP | Z2: Dealer Contribution with GST | AA2: Total Consumer Scheme with GST (OEM + Dealer) | AB2: Cash Discount | AC2: Accessories Discount | AD2: Shield Discount | AE2: Check | AF2: Acc Dsc Elg | AG2: Sheld Disc Elg
A3: G2C4AACVXB3C1C01QT | B3: VEERO | C3: 1.6XXL CBC V2 | D3: 669909 | E3: 18 | F3: 120584 | G3: 790493 | H3: 0 | I3: 28820 | J3: 5188 | K3: 824500 | L3: 46610 | M3: 55000 | N3: 0 | O3: 0 | P3: =M3+O3 -> 55000 | Q3: 35000 | R3: 20000 | S3: 0 | T3: =P3-SUM(Q3:S3) -> 0 | U3: 0.7 | V3: 1 | W3: 0 | X3: 0 | Y3: 0 | Z3: 0 | AA3: =X3+Z3 -> 0 | AB3: 0 | AC3: 0 | AD3: 0 | AE3: =AA3-SUM(AB3:AD3) -> 0 | AF3: 0.7 | AG3: 1
A4: G2D4AACVXB3F1A01WT | B4: VEERO | C4: 1.5XXL SD V2 - Airbag | D4: 693517 | E4: 18 | F4: 124833 | G4: 818350 | H4: 0 | I4: 29788 | J4: 5362 | K4: 853500 | L4: 46610 | M4: 55000 | N4: 0 | O4: 0 | P4: =M4+O4 -> 55000 | Q4: 35000 | R4: 20000 | S4: 0 | T4: =P4-SUM(Q4:S4) -> 0 | U4: 0.7 | V4: 1 | W4: 0 | X4: 0 | Y4: 0 | Z4: 0 | AA4: =X4+Z4 -> 0 | AB4: 0 | AC4: 0 | AD4: 0 | AE4: =AA4-SUM(AB4:AD4) -> 0 | AF4: 0.7 | AG4: 1
A5: G2D4AACVXB3F1A01QT | B5: VEERO | C5: 1.5XXL SD V2 - Airbag | D5: 693517 | E5: 18 | F5: 124833 | G5: 818350 | H5: 0 | I5: 29788 | J5: 5362 | K5: 853500 | L5: 46610 | M5: 55000 | N5: 0 | O5: 0 | P5: =M5+O5 -> 55000 | Q5: 35000 | R5: 20000 | S5: 0 | T5: =P5-SUM(Q5:S5) -> 0 | U5: 0.7 | V5: 1 | W5: 0 | X5: 0 | Y5: 0 | Z5: 0 | AA5: =X5+Z5 -> 0 | AB5: 0 | AC5: 0 | AD5: 0 | AE5: =AA5-SUM(AB5:AD5) -> 0 | AF5: 0.7 | AG5: 1
A6: PKN2BAADBS6PSFA3WD | B6: MAXX CITY | C6: MAXX CITY 1.3 LX BS6.2 - Special Edition | D6: 621615 | E6: 18 | F6: 111891 | G6: 733506 | H6: 0 | I6: 33215 | J6: 5979 | K6: 772700 | L6: 33898 | M6: 40000 | N6: 0 | O6: 0 | P6: =M6+O6 -> 40000 | Q6: 25000 | R6: 15000 | S6: 0 | T6: =P6-SUM(Q6:S6) -> 0 | U6: 0.7 | V6: 1 | W6: 0 | X6: 0 | Y6: 0 | Z6: 0 | AA6: =X6+Z6 -> 0 | AB6: 0 | AC6: 0 | AD6: 0 | AE6: =AA6-SUM(AB6:AD6) -> 0 | AF6: 0.7 | AG6: 1
A7: G2E4AACUXB3F1A01WT | B7: VEERO | C7: 1.5XXL SD V4 - Airbag | D7: 717041 | E7: 18 | F7: 129067 | G7: 846108 | H7: 0 | I7: 30840 | J7: 5551 | K7: 882500 | L7: 38136 | M7: 45000 | N7: 0 | O7: 0 | P7: =M7+O7 -> 45000 | Q7: 25000 | R7: 20000 | S7: 0 | T7: =P7-SUM(Q7:S7) -> 0 | U7: 0.7 | V7: 1 | W7: 0 | X7: 0 | Y7: 0 | Z7: 0 | AA7: =X7+Z7 -> 0 | AB7: 0 | AC7: 0 | AD7: 0 | AE7: =AA7-SUM(AB7:AD7) -> 0 | AF7: 0.7 | AG7: 1
A8: G2C4AACVXB3C1A01WT | B8: VEERO | C8: 1.5XXL CBC V2 | D8: 669909 | E8: 18 | F8: 120584 | G8: 790493 | H8: 0 | I8: 28820 | J8: 5188 | K8: 824500 | L8: 46610 | M8: 55000 | N8: 0 | O8: 0 | P8: =M8+O8 -> 55000 | Q8: 35000 | R8: 20000 | S8: 0 | T8: =P8-SUM(Q8:S8) -> 0 | U8: 0.7 | V8: 1 | W8: 0 | X8: 0 | Y8: 0 | Z8: 0 | AA8: =X8+Z8 -> 0 | AB8: 0 | AC8: 0 | AD8: 0 | AE8: =AA8-SUM(AB8:AD8) -> 0 | AF8: 0.7 | AG8: 1
A9: G2C4AACVXB3C1A01QT | B9: VEERO | C9: 1.5XXL CBC V2 | D9: 669909 | E9: 18 | F9: 120584 | G9: 790493 | H9: 0 | I9: 28820 | J9: 5188 | K9: 824500 | L9: 46610 | M9: 55000 | N9: 0 | O9: 0 | P9: =M9+O9 -> 55000 | Q9: 35000 | R9: 20000 | S9: 0 | T9: =P9-SUM(Q9:S9) -> 0 | U9: 0.7 | V9: 1 | W9: 0 | X9: 0 | Y9: 0 | Z9: 0 | AA9: =X9+Z9 -> 0 | AB9: 0 | AC9: 0 | AD9: 0 | AE9: =AA9-SUM(AB9:AD9) -> 0 | AF9: 0.7 | AG9: 1
A10: G2C4AACVXB3C1C01WT | B10: VEERO | C10: 1.6XXL CBC V2 | D10: 669909 | E10: 18 | F10: 120584 | G10: 790493 | H10: 0 | I10: 28820 | J10: 5188 | K10: 824500 | L10: 46610 | M10: 55000 | N10: 0 | O10: 0 | P10: =M10+O10 -> 55000 | Q10: 35000 | R10: 20000 | S10: 0 | T10: =P10-SUM(Q10:S10) -> 0 | U10: 0.7 | V10: 1 | W10: 0 | X10: 0 | Y10: 0 | Z10: 0 | AA10: =X10+Z10 -> 0 | AB10: 0 | AC10: 0 | AD10: 0 | AE10: =AA10-SUM(AB10:AD10) -> 0 | AF10: 0.7 | AG10: 1

Sheet Price List BEV
L1: Current VIN | W1: Old VIN
A2: Model Code | B2: OEM Model | C2: OEM Variant | D2: Asse Value with Freight | E2: GST | F2: GST Amount | G2: MM Inv Amt | H2: Dealer Margin | I2: Dealer Handling | J2: GST Amount 1 | K2: Ex-Showroom Price ORG | L2: OEM Scheme @ BNDP | M2: OEM Scheme with GST | N2: Dealer Cont @ BNDP | O2: Dealer Contribution with GST | P2: Total Consumer Scheme with GST (OEM + Dealer) | Q2: Cash Discount | R2: Accessories Discount | S2: Shield Discount | T2: Check | U2: Acc Dsc Elg | V2: Sheld Disc Elg | W2: OEM Scheme @ BNDP | X2: OEM Scheme with GST | Y2: Dealer Cont @ BNDP | Z2: Dealer Contribution with GST | AA2: Total Consumer Scheme with GST (OEM + Dealer) | AB2: Cash Discount | AC2: Accessories Discount | AD2: Shield Discount | AE2: Check | AF2: Acc Dsc Elg | AG2: Sheld Disc Elg
A3: BW62AB717MC01D02BN | B3: XEV9S | C3: XEV 9S TWO ABOVE B79 R18 7STR NCH | D3: 2393579 | E3: 5 | F3: 119679 | G3: 2513258 | H3: 77850 | I3: 0 | J3: 3893 | K3: 2595001 | L3: 0 | M3: 0 | N3: 0 | O3: 0 | P3: 0 | Q3: 0 | R3: =P3-Q3 -> 0 | S3: =P3-Q3-R3 -> 0 | T3: 0 | U3: 0.7 | V3: 1 | W3: 0 | X3: 0 | Y3: 0 | Z3: 0 | AA3: 0 | AB3: 0 | AC3: 0 | AD3: 0 | AE3: 0 | AF3: 0.7 | AG3: 1
A4: BM32AB715MB01D00WQ | B4: XEV9E | C4: XEV 9E TWO B79 R19 C11 | D4: 2513488 | E4: 5 | F4: 125674 | G4: 2639162 | H4: 81750 | I4: 0 | J4: 4088 | K4: 2725000 | L4: 66667 | M4: 70000 | N4: 19048 | O4: 20000 | P4: 90000 | Q4: 70000 | R4: 0 | S4: 0 | T4: 20000 | U4: 0.7 | V4: 1 | W4: 0 | X4: 0 | Y4: 0 | Z4: 0 | AA4: 0 | AB4: 0 | AC4: 0 | AD4: 0 | AE4: 0 | AF4: 0.7 | AG4: 1
A5: BM32AB715MB01D02RV | B5: XEV9E | C5: XEV 9E TWO B79 R19 NCH | D5: 2444310 | E5: 5 | F5: 122216 | G5: 2566526 | H5: 79500 | I5: 0 | J5: 3975 | K5: 2650001 | L5: 66667 | M5: 70000 | N5: 19048 | O5: 20000 | P5: 90000 | Q5: 70000 | R5: 0 | S5: 0 | T5: 20000 | U5: 0.7 | V5: 1 | W5: 0 | X5: 0 | Y5: 0 | Z5: 0 | AA5: 0 | AB5: 0 | AC5: 0 | AD5: 0 | AE5: 0 | AF5: 0.7 | AG5: 1
A6: BM32AF715MB01F02XM | B6: XEV9E | C6: XEV 9e THREE CL B79 R19 NCH | D6: 2707188 | E6: 5 | F6: 135359 | G6: 2842547 | H6: 88050 | I6: 0 | J6: 4403 | K6: 2935000 | L6: 0 | M6: 0 | N6: 0 | O6: 0 | P6: 0 | Q6: 0 | R6: 0 | S6: 0 | T6: 0 | U6: 0.7 | V6: 1 | W6: 0 | X6: 0 | Y6: 0 | Z6: 0 | AA6: 0 | AB6: 0 | AC6: 0 | AD6: 0 | AE6: 0 | AF6: 0.7 | AG6: 1
A7: BM12AQ715MB01B02OG | B7: BE6 FE | C7: BE 6 FE3 B79 R20 NCH | D7: 2258909 | E7: 5 | F7: 112945 | G7: 2371854 | H7: 73470 | I7: 0 | J7: 3674 | K7: 2448998 | L7: 95238 | M7: 100000 | N7: 0 | O7: 0 | P7: 100000 | Q7: 80000 | R7: 0 | S7: 0 | T7: 20000 | U7: 0.7 | V7: 1 | W7: 0 | X7: 0 | Y7: 0 | Z7: 0 | AA7: 0 | AB7: 0 | AC7: 0 | AD7: 0 | AE7: 0 | AF7: 0.7 | AG7: 1
A8: BW62AC717MB01D00WQ | B8: XEV9S | C8: XEV 9S THREE B79 R18 7STR C11 | D8: 2638010 | E8: 5 | F8: 131901 | G8: 2769911 | H8: 85800 | I8: 0 | J8: 4290 | K8: 2860001 | L8: 0 | M8: 0 | N8: 0 | O8: 0 | P8: 0 | Q8: 0 | R8: 0 | S8: 0 | T8: 0 | U8: 0.7 | V8: 1 | W8: 0 | X8: 0 | Y8: 0 | Z8: 0 | AA8: 0 | AB8: 0 | AC8: 0 | AD8: 0 | AE8: 0 | AF8: 0.7 | AG8: 1
A9: BM12AH515MB02D02OG | B9: BE6 | C9: BE 6 One above B59 R19 NCH | D9: 1890882 | E9: 5 | F9: 94544 | G9: 1985426 | H9: 61500 | I9: 0 | J9: 3075 | K9: 2050001 | L9: 57143 | M9: 60000 | N9: 19048 | O9: 20000 | P9: 80000 | Q9: 60000 | R9: 0 | S9: 0 | T9: 20000 | U9: 0.7 | V9: 1 | W9: 0 | X9: 0 | Y9: 0 | Z9: 0 | AA9: 0 | AB9: 0 | AC9: 0 | AD9: 0 | AE9: 0 | AF9: 0.7 | AG9: 1
A10: BW62AD717MB01D02WQ | B10: XEV9S | C10: XEV 9S THREE ABOVE B79 R18 7STR NCH | D10: 2762531 | E10: 5 | F10: 138127 | G10: 2900658 | H10: 89850 | I10: 0 | J10: 4493 | K10: 2995000 | L10: 0 | M10: 0 | N10: 0 | O10: 0 | P10: 0 | Q10: 0 | R10: 0 | S10: 0 | T10: 0 | U10: 0.7 | V10: 1 | W10: 0 | X10: 0 | Y10: 0 | Z10: 0 | AA10: 0 | AB10: 0 | AC10: 0 | AD10: 0 | AE10: 0 | AF10: 0.7 | AG10: 1
A11: BM12AB515MB02D02XJ | B11: BE6 | C11: BE 6 Two B59 R19 NCH | D11: 2020015 | E11: 5 | F11: 101001 | G11: 2121016 | H11: 65700 | I11: 0 | J11: 3285 | K11: 2190001 | L11: 123810 | M11: 130001 | N11: 19048 | O11: 20000 | P11: 150001 | Q11: 130000 | R11: 0 | S11: 0 | T11: 20001 | U11: 0.7 | V11: 1 | W11: 0 | X11: 0 | Y11: 0 | Z11: 0 | AA11: 0 | AB11: 0 | AC11: 0 | AD11: 0 | AE11: 0 | AF11: 0.7 | AG11: 1

Sheet Price List LMM
A1: City | B1: OEM Model | C1: OEM Variant | D1: Model Code | E1: Assesable Value | F1: Freight New | G1: GST% | H1: Cess% | I1: GST Amount | J1: LMM Inv Amt | K1: New Dealer Margin | L1: Extra Handling | M1: GST Amount 1 | N1: Ex Showroom Price | O1: Ex Showroom Price(Org) | P1: VIN Scheme | R1: OEM Scheme @ BNDP | S1: Dealer Cont @ BNDP | T1: Dealer Contribution with GST | U1: Total Consumer Scheme with GST (OEM + Dealer)
A2: BIKANER | B2: E ALFA PLUS | C2: E-ALFA+ SOLT WT | D2: 1EV2DH5T3FZG1WS | E2: 151038 | F2: 4559 | G2: 5 | H2: 0 | I2: 7780 | J2: 163376 | K2: 10327 | L2: 0 | M2: 516 | N2: 174219 | O2: 177219 | P2: 10876 | R2: =P2/(100%+G2%) -> 10358.095 | S2: =T2/(100%+G2%) -> 2880 | T2: 3024 | U2: =P2+T2 -> 13900
A3: BIKANER | B3: E ALFA PLUS | C3: E-ALFA+ WARM RED | D3: 1EV2DH5T3FZG1WR | E3: 151038 | F3: 4559 | G3: 5 | H3: 0 | I3: 7780 | J3: 163376 | K3: 10327 | L3: 0 | M3: 516 | N3: 174219 | O3: 177219 | P3: 10876 | R3: =P3/(100%+G3%) -> 10358.095 | S3: =T3/(100%+G3%) -> 2880 | T3: 3024 | U3: =P3+T3 -> 13900
A4: BIKANER | B4: E ALFA PLUS | C4: E-ALFA+ NISS BLU | D4: 1EV2DH5T3FZG1NB | E4: 151038 | F4: 4559 | G4: 5 | H4: 0 | I4: 7780 | J4: 163376 | K4: 10327 | L4: 0 | M4: 516 | N4: 174219 | O4: 177219 | P4: 10876 | R4: =P4/(100%+G4%) -> 10358.095 | S4: =T4/(100%+G4%) -> 2880 | T4: 3024 | U4: =P4+T4 -> 13900
A5: BIKANER | B5: ZEO | C5: MAHINDRA ZEO V2 | D5: AP61WLED2BB18A00WD | E5: 7,26,023 | F5: 10011 | G5: 5 | H5: - | I5: 36802 | J5: 7,72,836 | K5: 31663 | L5: 0 | M5: 1583 | N5: 8,06,081 | O5: 8,06,081 | P5: 0 | R5: =P5/(100%+G5%) -> 0 | S5: =T5/(100%+G5%) -> 0 | U5: =P5+T5 -> 0
A6: BIKANER | B6: ZEO | C6: MAHINDRA ZEO V2-DEMO | D6: AP61WLED2BB18A99WD | E6: 7,26,023 | F6: 10011 | G6: 5 | H6: - | I6: 36802 | J6: 7,72,836 | K6: 31663 | L6: 0 | M6: 1583 | N6: 8,06,081 | O6: 8,06,081 | P6: 0 | R6: =P6/(100%+G6%) -> 0 | S6: =T6/(100%+G6%) -> 0 | U6: =P6+T6 -> 0
A7: BIKANER | B7: ZEO | C7: MAHINDRA ZEO V2 DV 200 | D7: AP61WLED2BB18J00WD | E7: 7,36,319 | F7: 29122 | G7: 5 | H7: - | I7: 38272 | J7: 8,03,713 | K7: 31640 | L7: 0 | M7: 1582 | N7: 8,36,935 | O7: 8,36,935 | P7: 0 | R7: =P7/(100%+G7%) -> 0 | S7: =T7/(100%+G7%) -> 0 | U7: =P7+T7 -> 0
A8: BIKANER | B8: ZEO | C8: MAHINDRA ZEO V2 DV 200-DEMO | D8: AP61WLED2BB18J99WD | E8: 7,36,319 | F8: 29122 | G8: 5 | H8: - | I8: 38272 | J8: 8,03,713 | K8: 31640 | L8: 0 | M8: 1582 | N8: 8,36,935 | O8: 8,36,935 | P8: 0 | R8: =P8/(100%+G8%) -> 0 | S8: =T8/(100%+G8%) -> 0 | U8: =P8+T8 -> 0

Sheet Price List LMM TZU
A1: City | B1: M.CODE | C1: Material Description | D1: Model Name | E1: Model Group | F1: Scheme | G1: Before GST | H1: New Base Price (Ex-Factory) | I1: Freight | J1: Diff/Adjustment | K1: Assessable Value | L1: GST on Assessable Value @ 5% | M1: LMM Billing Price before (PM E-DRIVE SUBSIDY) | N1: LMM Billing Price After (PM E-DRIVE SUBSIDY) | O1: New Dealer Marging | P1: Dealer GST @ 5% | Q1: Ex-Showroom Pre Subsidy | R1: Battery Capacity | S1: PM E-DRIVE SUBSIDY Subsidy | T1: Maharashtra State Subsidy | U1: Exshowroom Post Subsidy (PM E-DRIVE SUBSIDY) | V1: Scheme | W1: Final Transaction Price | Y1: OEM Scheme @ BNDP | Z1: Dealer Cont @ BNDP | AA1: Dealer Contribution with GST | AB1: Total Consumer Scheme with GST (OEM + Dealer)
A2: BIKANER | B2: 0000AMJ00030N | C2: TREO HRT | D2: TREO HRT | E2: TREO AUTO | F2: 20000 | G2: 19048 | H2: 3,00,752 | I2: 11875 | J2: - | K2: 3,12,627 | L2: 15631 | M2: 3,28,258 | N2: 3,28,258 | O2: 19518 | P2: 976 | Q2: 3,48,752 | U2: 3,48,752 | V2: 20000 | W2: 3,28,752 | Y2: =V2/(100%+5%) -> 19047.619 | Z2: =AA2/(100%+5%) -> 0 | AA2: 0 | AB2: =V2+AA2 -> 20000
A3: BIKANER | B3: 0000AMJ00030N | C3: TREO HRT | D3: TREO HRT | E3: TREO AUTO | F3: 20000 | G3: 19048 | H3: 3,00,752 | I3: 11875 | J3: - | K3: 3,12,627 | L3: 15631 | M3: 3,28,258 | N3: 3,28,258 | O3: 19518 | P3: 976 | Q3: 3,48,752 | U3: 3,48,752 | V3: 20000 | W3: 3,28,752 | Y3: =V3/(100%+5%) -> 19047.619 | Z3: =AA3/(100%+5%) -> 0 | AA3: 0 | AB3: =V3+AA3 -> 20000
A4: BIKANER | B4: 0000AMJ00010N | C4: TREO SFT | D4: TREO SFT | E4: TREO AUTO | F4: 20000 | G4: 19048 | H4: 2,90,794 | I4: 11875 | J4: - | K4: 3,02,669 | L4: 15133 | M4: 3,17,802 | N4: 3,17,802 | O4: 19625 | P4: 981 | Q4: 3,38,408 | U4: 3,38,408 | V4: 20000 | W4: 3,18,408 | Y4: =V4/(100%+5%) -> 19047.619 | Z4: =AA4/(100%+5%) -> 0 | AA4: 0 | AB4: =V4+AA4 -> 20000
A5: BIKANER | B5: 1EP2GN4TVNUG1TW | C5: UDO ST | D5: UDO ST | E5: UDO | F5: 25300 | G5: 24095 | H5: 3,45,095 | I5: 14000 | J5: - | K5: 3,59,095 | L5: 17955 | M5: 3,77,050 | N5: 3,77,050 | O5: 17000 | P5: 850 | Q5: 3,94,900 | U5: 3,94,900 | V5: 25300 | W5: 3,69,600 | Y5: =V5/(100%+5%) -> 24095.238 | Z5: =AA5/(100%+5%) -> 0 | AA5: 0 | AB5: =V5+AA5 -> 25300
A6: BIKANER | B6: 1EP2GN4TVNUG1WS | C6: UDO ST | D6: UDO ST | E6: UDO | F6: 25300 | G6: 24095 | H6: 3,45,095 | I6: 14000 | J6: - | K6: 3,59,095 | L6: 17955 | M6: 3,77,050 | N6: 3,77,050 | O6: 17000 | P6: 850 | Q6: 3,94,900 | U6: 3,94,900 | V6: 25300 | W6: 3,69,600 | Y6: =V6/(100%+5%) -> 24095.238 | Z6: =AA6/(100%+5%) -> 0 | AA6: 0 | AB6: =V6+AA6 -> 25300
A7: BIKANER | B7: 1EP2GN4TVNUG1YB | C7: UDO ST | D7: UDO ST | E7: UDO | F7: 25300 | G7: 24095 | H7: 3,45,095 | I7: 14000 | J7: - | K7: 3,59,095 | L7: 17955 | M7: 3,77,050 | N7: 3,77,050 | O7: 17000 | P7: 850 | Q7: 3,94,900 | U7: 3,94,900 | V7: 25300 | W7: 3,69,600 | Y7: =V7/(100%+5%) -> 24095.238 | Z7: =AA7/(100%+5%) -> 0 | AA7: 0 | AB7: =V7+AA7 -> 25300

Sheet Price List CSD
K1: 1- Basic Price to CSD | M1: 2 - Discount to CSD | N1: 3 - Consumer Scheme Before GST | O1: 4 - Net Price Before GST | P1: 5 - GST Rate | Q1: 6 - GST Amount | R1: 7 - Invoice Amt (Ex SR Price) (LS OrderAmt) | U1: 9 - GST Discount @ 50% | V1: 8 - CSD Charge @ 0.5% | W1: 10 - DD Amount (Inclusive of CSD Charge)
A2: Model Code | B2: OEM Model | C2: OEM Variant | D2: Custom Model | E2: Custom Variant | F2: Display Name | G2: City | H2: Asse Value with Freight | I2: Retail Dealer Margin | J2: DEALER MARGIN DISCOUNT | K2: BASIC Price Including CSD Dealer Margin | L2: CSD% Discount | M2: CSD Discount | N2: Market Scheme at BNDP | O2: CSD Basic with Discount | P2: GST % | Q2: GST Amount | R2: CSD Final Price | S2: Amount to be claimed by Dealer | T2: GST @ 50% Discount | U2: GST Amount on CSD Basic with Discount | V2: CSD Profit @ 0.50% | W2: CSD Final Price with GST Concession
A3: BM12AJ515MB01B00RQ | B3: BE6 | C3: BE 6 Three Select B59 R19 C11 | D3: =VLOOKUP($A3,'Vehicle Info'!$A:$W,18,0) -> #N/A | E3: =VLOOKUP($A3,'Vehicle Info'!$A:$W,19,0) -> #N/A | F3: =VLOOKUP($A3,'Vehicle Info'!$A:$W,20,0) -> #N/A | G3: BIKANER | H3: 23,29,012 | I3: 75750 | J3: 38200 | K3: 23,66,562 | L3: 0.27 | M3: 6288 | N3: 66667 | O3: 22,93,607 | P3: 5 | Q3: 1,14,680 | R3: 24,08,288 | S3: 6603 | T3: 2.5 | U3: 57340 | V3: 11468 | W3: 23,62,415
A4: BM12AJ515MB01B00XJ | B4: BE6 | C4: BE 6 Three Select B59 R19 C11 | D4: =VLOOKUP($A4,'Vehicle Info'!$A:$W,18,0) -> #N/A | E4: =VLOOKUP($A4,'Vehicle Info'!$A:$W,19,0) -> #N/A | F4: =VLOOKUP($A4,'Vehicle Info'!$A:$W,20,0) -> #N/A | G4: BIKANER | H4: 23,29,012 | I4: 75750 | J4: 38200 | K4: 23,66,562 | L4: 0.27 | M4: 6288 | N4: 66667 | O4: 22,93,607 | P4: 5 | Q4: 1,14,680 | R4: 24,08,288 | S4: 6603 | T4: 2.5 | U4: 57340 | V4: 11468 | W4: 23,62,415
A5: BM12AJ515MB01B00OG | B5: BE6 | C5: BE 6 Three Select B59 R19 C11 | D5: =VLOOKUP($A5,'Vehicle Info'!$A:$W,18,0) -> #N/A | E5: =VLOOKUP($A5,'Vehicle Info'!$A:$W,19,0) -> #N/A | F5: =VLOOKUP($A5,'Vehicle Info'!$A:$W,20,0) -> #N/A | G5: BIKANER | H5: 23,29,012 | I5: 75750 | J5: 38200 | K5: 23,66,562 | L5: 0.27 | M5: 6288 | N5: 66667 | O5: 22,93,607 | P5: 5 | Q5: 1,14,680 | R5: 24,08,288 | S5: 6603 | T5: 2.5 | U5: 57340 | V5: 11468 | W5: 23,62,415
A6: BM12AJ515MB01B00QK | B6: BE6 | C6: BE 6 Three Select B59 R19 C11 | D6: =VLOOKUP($A6,'Vehicle Info'!$A:$W,18,0) -> #N/A | E6: =VLOOKUP($A6,'Vehicle Info'!$A:$W,19,0) -> #N/A | F6: =VLOOKUP($A6,'Vehicle Info'!$A:$W,20,0) -> #N/A | G6: BIKANER | H6: 23,29,012 | I6: 75750 | J6: 38200 | K6: 23,66,562 | L6: 0.27 | M6: 6288 | N6: 66667 | O6: 22,93,607 | P6: 5 | Q6: 1,14,680 | R6: 24,08,288 | S6: 6603 | T6: 2.5 | U6: 57340 | V6: 11468 | W6: 23,62,415
A7: AZ1036YJT2A4FA01SF | B7: Scorpio-N | C7: Z2 D MT 2WD 7 STR - E BS6.2 - New | D7: =VLOOKUP($A7,'Vehicle Info'!$A:$W,18,0) -> #N/A | E7: =VLOOKUP($A7,'Vehicle Info'!$A:$W,19,0) -> #N/A | F7: =VLOOKUP($A7,'Vehicle Info'!$A:$W,20,0) -> #N/A | G7: BIKANER | H7: 9,57,358 | I7: 41928 | J7: 4416 | K7: 9,94,869 | L7: 1 | M7: 9574 | N7: - | O7: 9,85,296 | P7: 40 | Q7: 3,94,118 | R7: 13,79,414 | S7: 13403 | T7: 20 | U7: 1,97,059 | V7: 4926 | W7: 11,87,281
A8: AZ1036YJT2A4FA01XH | B8: Scorpio-N | C8: Z2 D MT 2WD 7 STR - E BS6.2 - New | D8: =VLOOKUP($A8,'Vehicle Info'!$A:$W,18,0) -> #N/A | E8: =VLOOKUP($A8,'Vehicle Info'!$A:$W,19,0) -> #N/A | F8: =VLOOKUP($A8,'Vehicle Info'!$A:$W,20,0) -> #N/A | G8: BIKANER | H8: 9,57,358 | I8: 41928 | J8: 4416 | K8: 9,94,869 | L8: 1 | M8: 9574 | N8: - | O8: 9,85,296 | P8: 40 | Q8: 3,94,118 | R8: 13,79,414 | S8: 13403 | T8: 20 | U8: 1,97,059 | V8: 4926 | W8: 11,87,281
A9: AZ1096YJT2A4FA01WQ | B9: Scorpio-N | C9: Z2 D MT 2WD 7 STR - E BS6.2 - New | D9: =VLOOKUP($A9,'Vehicle Info'!$A:$W,18,0) -> #N/A | E9: =VLOOKUP($A9,'Vehicle Info'!$A:$W,19,0) -> #N/A | F9: =VLOOKUP($A9,'Vehicle Info'!$A:$W,20,0) -> #N/A | G9: BIKANER | H9: 9,57,358 | I9: 41928 | J9: 4416 | K9: 9,94,869 | L9: 1 | M9: 9574 | N9: - | O9: 9,85,296 | P9: 40 | Q9: 3,94,118 | R9: 13,79,414 | S9: 13403 | T9: 20 | U9: 1,97,059 | V9: 4926 | W9: 11,87,281
A10: AZ1096YJT2A4FA01XJ | B10: Scorpio-N | C10: Z2 D MT 2WD 7 STR - E BS6.2 - New | D10: =VLOOKUP($A10,'Vehicle Info'!$A:$W,18,0) -> #N/A | E10: =VLOOKUP($A10,'Vehicle Info'!$A:$W,19,0) -> #N/A | F10: =VLOOKUP($A10,'Vehicle Info'!$A:$W,20,0) -> #N/A | G10: BIKANER | H10: 9,57,358 | I10: 41928 | J10: 4416 | K10: 9,94,869 | L10: 1 | M10: 9574 | N10: - | O10: 9,85,296 | P10: 40 | Q10: 3,94,118 | R10: 13,79,414 | S10: 13403 | T10: 20 | U10: 1,97,059 | V10: 4926 | W10: 11,87,281
A11: AZ1096YJT2A4FA01SF | B11: Scorpio-N | C11: Z2 D MT 2WD 7 STR - E BS6.2 - New | D11: =VLOOKUP($A11,'Vehicle Info'!$A:$W,18,0) -> #N/A | E11: =VLOOKUP($A11,'Vehicle Info'!$A:$W,19,0) -> #N/A | F11: =VLOOKUP($A11,'Vehicle Info'!$A:$W,20,0) -> #N/A | G11: BIKANER | H11: 9,57,358 | I11: 41928 | J11: 4416 | K11: 9,94,869 | L11: 1 | M11: 9574 | N11: - | O11: 9,85,296 | P11: 40 | Q11: 3,94,118 | R11: 13,79,414 | S11: 13403 | T11: 20 | U11: 1,97,059 | V11: 4926 | W11: 11,87,281

Sheet CSD Index Codes
A1: OEM Model | B1: OEM Variant | C1: CSD Index Code
A2: Bolero | B2: B4 BS6.2 - Refresh | C2: 64361
A3: Bolero | B3: B6 OPT BS6.2 - Refresh | C3: 64829
A4: Marazzo | B4: M2 7 Str BS6.2 | C4: 64921
A5: Marazzo | B5: M4+ 7 Str BS6.2 | C5: 64922
A6: Marazzo | B6: M6+ 7 Str BS6.2 | C6: 64923
A7: PICKUP | B7: BOL CAMPER GOLD ZX 2WD BS6.2 - NEW | C7: 64365-L
A8: Thar | B8: AX OPT D MT 4WD 4S HT BS6.2 | C8: 65288
A9: Thar | B9: LX P AT 4WD 4S HT BS6.2 | C9: 65282
A10: Thar | B10: LXT D AT 4WD 4S HT BS6.2 | C10: 65284
A11: Thar | B11: LXT D MT 2WD 4S HT BS6.2 | C11: 67687
A12: Thar | B12: LXT D MT 4WD 4S HT BS6.2 | C12: 65280
A13: Thar | B13: LXT P AT 2WD 4S HT BS6.2 | C13: 67688
A14: Thar | B14: LXT P MT 4WD 4S HT BS6.2 | C14: 65283
A15: Thar | B15: AXT D MT 2WD 4S HT BS6.2 | C15: 67686
A16: Scorpio-N | B16: Z6 D MT 2WD 7 STR BS6.2 - New | C16: 67352-K
A17: Scorpio-N | B17: Z8 D MT 2WD 7 STR BS6.2 - N | C17: 67353-X
A18: Scorpio-N | B18: Z6 D AT 2WD 7 STR BS6.2 - New | C18: 67684-A
A19: Scorpio-N | B19: Z8 D AT 2WD 7 STR BS6.2 - N | C19: 67685-D
A20: Scorpio-N | B20: Z2 D MT 2WD 7 STR - E BS6.2 - New | C20: 67681
A21: Scorpio-N | B21: Z4 D MT 2WD 7 STR - E BS6.2 - New | C21: 67682
A22: Scorpio-N | B22: Z4 G MT 2WD 7 STR - E BS6.2 - New | C22: 67683
A23: Scorpio-N | B23: Z8 L D AT 2WD 6 STR BS6.2 - N - ADAS | C23: 65292-I
A24: Scorpio-N | B24: Z8 L D AT 2WD 7 STR BS6.2 - N - ADAS | C24: 65293-S
A25: Scorpio-N | B25: Z8 L D AT 2WD 7 STR BS6.2 - N - Black Edition - ADAS | C25: 65294-T
A26: Scorpio-N | B26: Z8 L D AT 4WD 7 STR BS6.2 - N - ADAS | C26: 65295-K
A27: Scorpio-N | B27: Z8 L D AT 4WD 7 STR BS6.2 - N - Black Edition - ADAS | C27: 65296-X
A28: Scorpio-N | B28: Z8 L D MT 2WD 6 STR BS6.2 - N - ADAS | C28: 65297-A
A29: Scorpio-N | B29: Z8 L D MT 2WD 7 STR BS6.2 - N - ADAS | C29: 65298-D
A30: Scorpio-N | B30: Z8 L D MT 2WD 7 STR BS6.2 - N - Black Edition - ADAS | C30: 65299-E
A31: Scorpio-N | B31: Z8 L D MT 4WD 7 STR BS6.2 - N - ADAS | C31: 65300-L
A32: Scorpio-N | B32: Z8 L D MT 4WD 7 STR BS6.2 - N - Black Edition - ADAS | C32: 65301-P
A33: Scorpio-N | B33: Z8 L G AT 2WD 6 STR BS6.2 - N - ADAS | C33: 65302-H
A34: Scorpio-N | B34: Z8 L G AT 2WD 7 STR BS6.2 - N - ADAS | C34: 65303-I
... A67: XUV700 | B67: AX7 PET MT 7 STR BS6.2 - EBONY | C67: 65322-L
A68: XUV400 | B68: EL PRO FC - Battery 39.4 Kwh - Charger 7.2 Kw - E | C68: 67356
A69: XUV400 | B69: EL PRO FC DT - Battery 39.4 Kwh - Charger 7.2 Kw - E | C69: 67357
A70: Bolero Neo | B70: N10 BS6.2 - R - Refresh | C70: 67677
A71: Bolero Neo | B71: N10 OPT BS6.2 - Refresh | C71: 67678
A72: Bolero Neo | B72: N4 BS6.2 - Refresh | C72: 67679
A73: Bolero Neo | B73: N8 BS6.2 - Refresh | C73: 67680
A74: Scorpio | B74: Classic S - 9 STR BS6.2 - New | C74: 67696-D
A75: Scorpio | B75: Classic S BS6.2 - New | C75: 67697-E
A76: Scorpio | B76: Classic S11 BS6.2 - New | C76: 67698-L
A77: XUV 3XO | B77: AX5 DS AS | C77: 67717-A
A78: XUV 3XO | B78: AX5 DS MT | C78: 67718-D
A79: XUV 3XO | B79: AX5 PM AT | C79: 67719-E
A80: XUV 3XO | B80: AX5 PM MT | C80: 67720-L
A81: XUV 3XO | B81: AX5L TGDI AT | C81: 67721-P
A82: XUV 3XO | B82: AX5L TGDI MT | C82: 67722-H
A83: XUV 3XO | B83: AX7 DS AS DT | C83: 65346-H
A84: XUV 3XO | B84: AX7 DS MT DT | C84: 65347-I
A85: XUV 3XO | B85: AX7 TGDI MT DT | C85: 65348-S
... A162: XUV7XO | B162: AX3 PET AT 7 STR | C162: 67911-S

Sheet Corporate
A1: OEM Model | B1: OEM Variant | C1: CAT B OEM | D1: CAT B DLR | E1: CAT B TOTAL | F1: BULK 1 (2-5) OEM | G1: BULK 1 (2-5) DLR | H1: BULK 1 (2-5) TOTAL | I1: CAT A OEM | J1: CAT A DLR | K1: CAT A TOTAL | L1: BULK 2 (6-10) OEM | M1: BULK 2 (6-10) DLR | N1: BULK 2 (6-10) TOTAL | O1: CAT F OEM | P1: CAT F DLR | Q1: CAT F TOTAL | R1: BULK 3 (11 & Above) OEM | S1: BULK 3 (11 & Above) DLR | T1: BULK 3 (11 & Above) TOTAL | U1: CAT Y (Premium) OEM | V1: CAT Y (Premium) DLR | W1: CAT Y (Premium) TOTAL | X1: CAT Z (Signature) OEM | Y1: CAT Z (Signature) DLR | Z1: CAT Z (Signature) TOTAL
A2: BE6 | C2: 0 | D2: 0 | E2: =C2+D2 -> 0 | F2: 0 | G2: 0 | H2: =F2+G2 -> 0 | I2: 0 | J2: 0 | K2: =I2+J2 -> 0 | L2: 0 | M2: 0 | N2: =L2+M2 -> 0 | O2: 20000 | P2: 10000 | Q2: =O2+P2 -> 30000 | R2: 20000 | S2: 10000 | T2: =R2+S2 -> 30000 | U2: 20000 | V2: 10000 | W2: =U2+V2 -> 30000 | X2: 20000 | Y2: 10000 | Z2: =X2+Y2 -> 30000
A3: BE6 FE | C3: 0 | D3: 0 | E3: =C3+D3 -> 0 | F3: 0 | G3: 0 | H3: =F3+G3 -> 0 | I3: 0 | J3: 0 | K3: =I3+J3 -> 0 | L3: 0 | M3: 0 | N3: =L3+M3 -> 0 | O3: 20000 | P3: 10000 | Q3: =O3+P3 -> 30000 | R3: 20000 | S3: 10000 | T3: =R3+S3 -> 30000 | U3: 20000 | V3: 10000 | W3: =U3+V3 -> 30000 | X3: 20000 | Y3: 10000 | Z3: =X3+Y3 -> 30000
A4: Bolero | C4: 900 | D4: 900 | E4: =C4+D4 -> 1800 | F4: 900 | G4: 900 | H4: =F4+G4 -> 1800 | I4: 1800 | J4: 900 | K4: =I4+J4 -> 2700 | L4: 1800 | M4: 900 | N4: =L4+M4 -> 2700 | O4: 2200 | P4: 1300 | Q4: =O4+P4 -> 3500 | R4: 2200 | S4: 1300 | T4: =R4+S4 -> 3500 | U4: 2500 | V4: 2500 | W4: =U4+V4 -> 5000 | X4: 18000 | Y4: 12000 | Z4: =X4+Y4 -> 30000
A5: Bolero Neo | C5: 1800 | D5: 900 | E5: =C5+D5 -> 2700 | F5: 1800 | G5: 900 | H5: =F5+G5 -> 2700 | I5: 2200 | J5: 1300 | K5: =I5+J5 -> 3500 | L5: 2200 | M5: 1300 | N5: =L5+M5 -> 3500 | O5: 2700 | P5: 1300 | Q5: =O5+P5 -> 4000 | R5: 2700 | S5: 1300 | T5: =R5+S5 -> 4000 | U5: 2500 | V5: 2500 | W5: =U5+V5 -> 5000 | X5: 18000 | Y5: 12000 | Z5: =X5+Y5 -> 30000
A6: Bolero Neo + | C6: 0 | D6: 0 | E6: =C6+D6 -> 0 | F6: 0 | G6: 0 | H6: =F6+G6 -> 0 | I6: 0 | J6: 0 | K6: =I6+J6 -> 0 | L6: 0 | M6: 0 | N6: =L6+M6 -> 0 | O6: 0 | P6: 0 | Q6: =O6+P6 -> 0 | R6: 0 | S6: 0 | T6: =R6+S6 -> 0 | U6: 2500 | V6: 2500 | W6: =U6+V6 -> 5000 | X6: 24000 | Y6: 16000 | Z6: =X6+Y6 -> 40000
A7: Marazzo | C7: 0 | D7: 0 | E7: =C7+D7 -> 0 | F7: 0 | G7: 0 | H7: =F7+G7 -> 0 | I7: 0 | J7: 0 | K7: =I7+J7 -> 0 | L7: 0 | M7: 0 | N7: =L7+M7 -> 0 | O7: 0 | P7: 0 | Q7: =O7+P7 -> 0 | R7: 0 | S7: 0 | T7: =R7+S7 -> 0 | U7: 2500 | V7: 2500 | W7: =U7+V7 -> 5000 | X7: 24000 | Y7: 16000 | Z7: =X7+Y7 -> 40000
A8: Scorpio | C8: 0 | D8: 0 | E8: =C8+D8 -> 0 | F8: 0 | G8: 0 | H8: =F8+G8 -> 0 | I8: 0 | J8: 0 | K8: =I8+J8 -> 0 | L8: 0 | M8: 0 | N8: =L8+M8 -> 0 | O8: 0 | P8: 0 | Q8: =O8+P8 -> 0 | R8: 0 | S8: 0 | T8: =R8+S8 -> 0 | U8: 2500 | V8: 2500 | W8: =U8+V8 -> 5000 | X8: 24000 | Y8: 16000 | Z8: =X8+Y8 -> 40000
A9: Scorpio-N | C9: 1800 | D9: 1800 | E9: =C9+D9 -> 3600 | F9: 1800 | G9: 1800 | H9: =F9+G9 -> 3600 | I9: 2300 | J9: 2300 | K9: =I9+J9 -> 4600 | L9: 2300 | M9: 2300 | N9: =L9+M9 -> 4600 | O9: 2800 | P9: 2800 | Q9: =O9+P9 -> 5600 | R9: 2800 | S9: 2800 | T9: =R9+S9 -> 5600 | U9: 3750 | V9: 3750 | W9: =U9+V9 -> 7500 | X9: 24000 | Y9: 16000 | Z9: =X9+Y9 -> 40000
A10: Thar | C10: 0 | D10: 0 | E10: =C10+D10 -> 0 | F10: 0 | G10: 0 | H10: =F10+G10 -> 0 | I10: 0 | J10: 0 | K10: =I10+J10 -> 0 | L10: 0 | M10: 0 | N10: =L10+M10 -> 0 | O10: 0 | P10: 0 | Q10: =O10+P10 -> 0 | R10: 0 | S10: 0 | T10: =R10+S10 -> 0 | U10: 2500 | V10: 2500 | W10: =U10+V10 -> 5000 | X10: 18000 | Y10: 12000 | Z10: =X10+Y10 -> 30000
A11: Thar Roxx | C11: 0 | D11: 0 | E11: =C11+D11 -> 0 | F11: 0 | G11: 0 | H11: =F11+G11 -> 0 | I11: 0 | J11: 0 | K11: =I11+J11 -> 0 | L11: 0 | M11: 0 | N11: =L11+M11 -> 0 | O11: 5000 | P11: 5000 | Q11: =O11+P11 -> 10000 | R11: 5000 | S11: 5000 | T11: =R11+S11 -> 10000 | U11: 7500 | V11: 7500 | W11: =U11+V11 -> 15000 | X11: 24000 | Y11: 16000 | Z11: =X11+Y11 -> 40000
A12: XEV9E | C12: 0 | D12: 0 | E12: =C12+D12 -> 0 | F12: 0 | G12: 0 | H12: =F12+G12 -> 0 | I12: 0 | J12: 0 | K12: =I12+J12 -> 0 | L12: 0 | M12: 0 | N12: =L12+M12 -> 0 | O12: 6000 | P12: 4000 | Q12: =O12+P12 -> 10000 | R12: 6000 | S12: 4000 | T12: =R12+S12 -> 10000 | U12: 6000 | V12: 4000 | W12: =U12+V12 -> 10000 | X12: 24000 | Y12: 16000 | Z12: =X12+Y12 -> 40000
A13: XEV9S | C13: 0 | D13: 0 | E13: =C13+D13 -> 0 | F13: 0 | G13: 0 | H13: =F13+G13 -> 0 | I13: 0 | J13: 0 | K13: =I13+J13 -> 0 | L13: 0 | M13: 0 | N13: =L13+M13 -> 0 | O13: 0 | P13: 0 | Q13: =O13+P13 -> 0 | R13: 0 | S13: 0 | T13: =R13+S13 -> 0 | U13: 0 | V13: 0 | W13: =U13+V13 -> 0 | X13: 0 | Y13: 0 | Z13: =X13+Y13 -> 0
... A52: ZOR GRAND RE | C52: 1000 | D52: 500 | E52: =C52+D52 -> 1500 | F52: 1000 | G52: 500 | H52: =F52+G52 -> 1500 | I52: 1200 | J52: 800 | K52: =I52+J52 -> 2000 | L52: 1200 | M52: 800 | N52: =L52+M52 -> 2000 | O52: 1500 | P52: 1000 | Q52: =O52+P52 -> 2500 | R52: 1500 | S52: 1000 | T52: =R52+S52 -> 2500 | U52: 0 | V52: 0 | W52: =U52+V52 -> 0 | X52: 2500 | Y52: 0 | Z52: =X52+Y52 -> 2500

Sheet Exchange
A1: OEM Model | B1: OEM Variant | C1: Exchange Bonus OEM | D1: Exchange Bonus DLR | E1: Exchange Bonus TOTAL | F1: Welcome Bonus OEM | G1: Welcome Bonus DLR | H1: Welcome Bonus TOTAL | I1: Scrap Scheme OEM | J1: Scrap Scheme DLR | K1: Scrap Scheme TOTAL
A2: BE6 | C2: 30000 | D2: 0 | E2: =C2+D2 -> 30000 | H2: =F2+G2 -> 0 | I2: 0 | K2: =I2+J2 -> 0
A3: BE6 FE | C3: 30000 | D3: 0 | E3: =C3+D3 -> 30000 | H3: =F3+G3 -> 0 | I3: 0 | K3: =I3+J3 -> 0
A4: Bolero | C4: 10000 | D4: 0 | E4: =C4+D4 -> 10000 | H4: =F4+G4 -> 0 | I4: 20000 | K4: =I4+J4 -> 20000
A5: Bolero Neo | C5: 10000 | D5: 0 | E5: =C5+D5 -> 10000 | H5: =F5+G5 -> 0 | I5: 20000 | K5: =I5+J5 -> 20000
A6: Bolero Neo + | C6: 10000 | D6: 0 | E6: =C6+D6 -> 10000 | H6: =F6+G6 -> 0 | I6: 20000 | K6: =I6+J6 -> 20000
A7: Marazzo | C7: 15000 | D7: 0 | E7: =C7+D7 -> 15000 | H7: =F7+G7 -> 0 | I7: 35000 | K7: =I7+J7 -> 35000
A8: Scorpio | C8: 20000 | D8: 0 | E8: =C8+D8 -> 20000 | H8: =F8+G8 -> 0 | I8: 20000 | K8: =I8+J8 -> 20000
A9: Scorpio-N | C9: 25000 | D9: 0 | E9: =C9+D9 -> 25000 | H9: =F9+G9 -> 0 | I9: 25000 | K9: =I9+J9 -> 25000
A10: Thar | C10: 0 | D10: 0 | E10: =C10+D10 -> 0 | H10: =F10+G10 -> 0 | I10: 20000 | K10: =I10+J10 -> 20000
A11: Thar Roxx | C11: 0 | D11: 0 | E11: =C11+D11 -> 0 | H11: =F11+G11 -> 0 | I11: 20000 | K11: =I11+J11 -> 20000
A12: XEV9E | C12: 30000 | D12: 0 | E12: =C12+D12 -> 30000 | H12: =F12+G12 -> 0 | I12: 0 | K12: =I12+J12 -> 0
A13: XEV9S | C13: 0 | D13: 0 | E13: =C13+D13 -> 0 | H13: =F13+G13 -> 0 | I13: 0 | K13: =I13+J13 -> 0
... A22: Supro | C22: 45000 | D22: 0 | E22: =C22+D22 -> 45000 | H22: =F22+G22 -> 0 | I22: 45000 | K22: =I22+J22 -> 45000
A23: VEERO | C23: 45000 | D23: 0 | E23: =C23+D23 -> 45000 | F23: 15000 | G23: 0 | H23: =F23+G23 -> 15000 | I23: 45000 | K23: =I23+J23 -> 45000
A24: ALFA LOAD DUO | C24: 4000 | D24: 0 | E24: =C24+D24 -> 4000 | H24: =F24+G24 -> 0 | I24: 0 | K24: =I24+J24 -> 0
A25: ALFA Load Plus | C25: 4000 | D25: 0 | E25: =C25+D25 -> 4000 | H25: =F25+G25 -> 0 | I25: 0 | K25: =I25+J25 -> 0
A26: ALFA Load Plus CNG | C26: 4000 | D26: 0 | E26: =C26+D26 -> 4000 | H26: =F26+G26 -> 0 | I26: 0 | K26: =I26+J26 -> 0
A27: ALFA PASS DUO | C27: 5000 | D27: 0 | E27: =C27+D27 -> 5000 | H27: =F27+G27 -> 0 | I27: 0 | K27: =I27+J27 -> 0
A28: ALFA Passenger CNG | C28: 5000 | D28: 0 | E28: =C28+D28 -> 5000 | H28: =F28+G28 -> 0 | I28: 0 | K28: =I28+J28 -> 0
A29: ALFA Passenger Comfy | C29: 5000 | D29: 0 | E29: =C29+D29 -> 5000 | H29: =F29+G29 -> 0 | I29: 0 | K29: =I29+J29 -> 0
A30: ALFA Passenger Delux | C30: 5000 | D30: 0 | E30: =C30+D30 -> 5000 | H30: =F30+G30 -> 0 | I30: 0 | K30: =I30+J30 -> 0
A31: E ALFA CARGO | C31: 5000 | D31: 0 | E31: =C31+D31 -> 5000 | H31: =F31+G31 -> 0 | I31: 0 | K31: =I31+J31 -> 0
A32: E ALFA PLUS | C32: 5000 | D32: 0 | E32: =C32+D32 -> 5000 | H32: =F32+G32 -> 0 | I32: 0 | K32: =I32+J32 -> 0
A33: E ALFA PLUS HT | C33: 5000 | D33: 0 | E33: =C33+D33 -> 5000 | H33: =F33+G33 -> 0 | I33: 0 | K33: =I33+J33 -> 0
A34: E ALFA SUPER | C34: 5000 | D34: 0 | E34: =C34+D34 -> 5000 | H34: =F34+G34 -> 0 | I34: 0 | K34: =I34+J34 -> 0
A35: JEETO CNG | C35: 5000 | D35: 0 | E35: =C35+D35 -> 5000 | H35: =F35+G35 -> 0 | I35: 0 | K35: =I35+J35 -> 0
... A51: ZOR GRAND RE | C51: 5000 | D51: 0 | E51: =C51+D51 -> 5000 | H51: =F51+G51 -> 0 | I51: 0 | K51: =I51+J51 -> 0

Sheet RSA
A1: Segment | B1: Model | C1: Standard Coverage | D1: Std + 1 Year | E1: Std + 2 Years | F1: Std + 3 Years | G1: Std + 4 Years | H1: Std + 5 Years
A2: BEV | B2: BE6 | C2: 3 Years | D2: 3499 | E2: 4999
A3: BEV | B3: BE6 FE | C3: 3 Years | D3: 3499 | E3: 4999
A4: BEV | B4: XEV9E | C4: 3 Years | D4: 3499 | E4: 4999
A5: BEV | B5: XEV9S | C5: 3 Years | D5: 3499 | E5: 4999
A6: PEROSNAL | B6: SCORPIO-N | C6: 3 Years | D6: 2021 | E6: 3019.62
A7: PEROSNAL | B7: THAR ROXX | C7: 3 Years | D7: 2021 | E7: 3019.62
A8: PERSONAL | B8: XUV400 | C8: 3 Years | D8: 2021 | E8: 3019.62
A9: PEROSNAL | B9: XUV 3XO | C9: 4 Years | D9: 2021
A10: PEROSNAL | B10: XUV3XO EV | C10: NA | D10: NA | E10: NA | F10: NA | G10: NA | H10: NA
A11: PEROSNAL | B11: XUV700 | C11: 3 Years | D11: 2021 | E11: 3019.62
A12: PEROSNAL | B12: XUV7XO | C12: 3 Years | D12: 2021 | E12: 3019.62
A13: PERSONAL | B13: BOLERO | C13: NIL | D13: 2021 | E13: 3020 | F13: 4070
A14: PERSONAL | B14: BOLERO NEO | C14: NIL | D14: 2021 | E14: 3020 | F14: 4070
A15: PERSONAL | B15: BOLERO NEO + | C15: NIL | D15: 2021 | E15: 3020 | F15: 4070
A16: PERSONAL | B16: MARAZZO | C16: NIL | D16: 2021 | E16: 3020 | F16: 4070
A17: PERSONAL | B17: SCORPIO | C17: 2 Years | D17: 2021 | E17: 3020 | F17: 4070
A18: PERSONAL | B18: THAR | C18: 2 Years | D18: 2021 | E18: 3020 | F18: 4070
A19: LMM | B19: ALFA LOAD DUO | C19: NIL | D19: 1307 | E19: 1964 | F19: 2620
A20: LMM | B20: ALFA LOAD PLUS | C20: NIL | D20: 1307 | E20: 1964 | F20: 2620
A21: LMM | B21: ALFA LOAD PLUS CNG | C21: NIL | D21: 1307 | E21: 1964 | F21: 2620
A22: LMM | B22: ALFA PASS DUO | C22: NIL | D22: 1307 | E22: 1964 | F22: 2620
A23: LMM | B23: ALFA PASSENGER CNG | C23: NIL | D23: 1307 | E23: 1964 | F23: 2620
A24: LMM | B24: ALFA PASSENGER COMFY | C24: NIL | D24: 1307 | E24: 1964 | F24: 2620
... A29: LMM | B29: E ALFA SUPER | C29: NIL | D29: 1510 | E29: 2328 | F29: 3147
A30: LMM | B30: JEETO CNG | C30: NIL
A31: LMM | B31: JEETO DIESEL | C31: NIL
A32: LMM | B32: JEETO PETROL | C32: NIL
A33: LMM | B33: JEETO STRONG CNG | C33: NIL
A34: LMM | B34: JEETO STRONG DIESEL | C34: NIL
A35: LMM | B35: TREO AUTO | C35: NIL | D35: 1510 | E35: 2328 | F35: 3147
A36: LMM | B36: TREO PLUS | C36: NIL | D36: 1510 | E36: 2328 | F36: 3147
A37: LMM | B37: TREO PLUS METAL | C37: NIL | D37: 1510 | E37: 2328 | F37: 3147
A38: LMM | B38: TREO METAL | C38: NIL | D38: 1510 | E38: 2328 | F38: 3147
A39: LMM | B39: TREO YAARI | C39: NIL | D39: 1510 | E39: 2328 | F39: 3147
A40: LMM | B40: TREO YAARI CARGO | C40: NIL | D40: 1510 | E40: 2328 | F40: 3147
A41: LMM | B41: TREO ZOR | C41: NIL | D41: 1510 | E41: 2328 | F41: 3147
A42: LMM | B42: UDO | C42: NIL | D42: 1510 | E42: 2328 | F42: 3147 | G42: 4823 | H42: 5970
A43: LMM | B43: ZEO | C43: NIL | D43: 1626 | E43: 2876 | F43: 4266 | G43: 5586 | H43: 6999
A44: LMM | B44: ZOR GRAND | C44: NIL | D44: 1510 | E44: 2328 | F44: 3147
A45: LMM | B45: ZOR GRAND R | C45: NIL | D45: 1510 | E45: 2328 | F45: 3147
A46: LMM | B46: ZOR GRAND RE | C46: NIL | D46: 1510 | E46: 2328 | F46: 3147
A47: COMMERCIAL | B47: MAXX CITY | C47: NIL | D47: 939 | E47: 1698 | F47: 2385
A48: COMMERCIAL | B48: MAXX HD | C48: NIL | D48: 939 | E48: 1698 | F48: 2385
A49: COMMERCIAL | B49: VEERO | C49: NIL | D49: 939 | E49: 1698 | F49: 2385
A50: COMMERCIAL | B50: CAMPER | C50: NIL | D50: 1519 | E50: 2299 | F50: 3199
A51: COMMERCIAL | B51: PICKUP | C51: NIL | D51: 1519 | E51: 2299 | F51: 3199
A52: COMMERCIAL | B52: SUPRO | C52: NIL | D52: 1519 | E52: 2299 | F52: 3199

Sheet Shield
A1: OEM Model | B1: OEM Variant | C1: Shield Pack | D1: Transmission | E1: Fuel | F1: Standard Warranty | G1: Shield Scheme 1 Name | H1: Shield Scheme 1 Amt | I1: Shield Scheme 2 Name | J1: Shield Scheme 2 Amt
A2: Bolero | F2: 3 Years OR 1 Lakh Kms, Whichever is Earlier | G2: 4th Year OR Up to 1 Lakh kms, Whichever is Earlier | H2: 8999 | I2: 4th & 5th Year OR Up to 1.2 Lakh Kms, Whichever is Earlier | J2: 16999
A3: Bolero Neo | F3: 3 Years OR 1 Lakh Kms, Whichever is Earlier | G3: 4th Year OR Up to 1 Lakh kms, Whichever is Earlier | H3: 9999 | I3: 4th & 5th Year OR Up to 1.2 Lakh Kms, Whichever is Earlier | J3: 18999
A4: Bolero Neo + | F4: 3 Years OR 1 Lakh Kms, Whichever is Earlier | G4: 4th Year OR Up to 1 Lakh kms, Whichever is Earlier | H4: 10999 | I4: 4th & 5th Year OR Up to 1.2 Lakh Kms, Whichever is Earlier | J4: 19999
A5: Marazzo | F5: 3 Years OR 1 Lakh Kms, Whichever is Earlier | G5: 4th Year OR 1.2 Lakh Kms, Whichever is Earlier | H5: 12979 | I5: 4th & 5th Year OR 1.5 Lakh Kms, Whichever is Earlier | J5: 18171
A6: Scorpio | F6: 3 Years OR 1 Lakh Kms, Whichever is Earlier | G6: 4th Year OR Up to 1 Lakh kms, Whichever is Earlier | H6: 17999 | I6: 4th & 5th Year OR Up to 1.2 Lakh Kms, Whichever is Earlier | J6: 32999
A7: Scorpio-N | D7: Manual | E7: Petrol | F7: 3 Years OR 1 Lakh Kms, Whichever is Earlier | G7: 4th Year OR 1.2 Lakh Kms, Whichever is Earlier | H7: 19999 | I7: 4th & 5th Year OR 1.5 Lakh Kms, Whichever is Earlier | J7: 35999
A8: Scorpio-N | D8: Automatic | E8: Petrol | F8: 3 Years OR 1 Lakh Kms, Whichever is Earlier | G8: 4th Year OR 1.2 Lakh Kms, Whichever is Earlier | H8: 23999 | I8: 4th & 5th Year OR 1.5 Lakh Kms, Whichever is Earlier | J8: 41999
A9: Scorpio-N | D9: Manual | E9: Diesel | F9: 3 Years OR 1 Lakh Kms, Whichever is Earlier | G9: 4th Year OR 1.2 Lakh Kms, Whichever is Earlier | H9: 20999 | I9: 4th & 5th Year OR 1.5 Lakh Kms, Whichever is Earlier | J9: 39999
A10: Scorpio-N | D10: Automatic | E10: Diesel | F10: 3 Years OR 1 Lakh Kms, Whichever is Earlier | G10: 4th Year OR 1.2 Lakh Kms, Whichever is Earlier | H10: 24999 | I10: 4th & 5th Year OR 1.5 Lakh Kms, Whichever is Earlier | J10: 49999
A11: Thar | E11: Petrol | F11: 3 Years OR 1 Lakh Kms, Whichever is Earlier | G11: 4th Year OR 1.2 Lakh Kms, Whichever is Earlier | H11: 16999 | I11: 4th & 5th Year OR 1.5 Lakh Kms, Whichever is Earlier | J11: 18999
A12: Thar | E12: Diesel | F12: 3 Years OR 1 Lakh Kms, Whichever is Earlier | G12: 4th Year OR 1.2 Lakh Kms, Whichever is Earlier | H12: 17999 | I12: 4th & 5th Year OR 1.5 Lakh Kms, Whichever is Earlier | J12: 19999
A13: Thar Roxx | D13: Manual | E13: Petrol | F13: 3 Years OR 1 Lakh Kms, Whichever is Earlier | G13: 4th Year OR 1.2 Lakh Kms, Whichever is Earlier | H13: 18999 | I13: 4th & 5th Year OR 1.5 Lakh Kms, Whichever is Earlier | J13: 32999
A14: Thar Roxx | D14: Automatic | E14: Petrol | F14: 3 Years OR 1 Lakh Kms, Whichever is Earlier | G14: 4th Year OR 1.2 Lakh Kms, Whichever is Earlier | H14: 22999 | I14: 4th & 5th Year OR 1.5 Lakh Kms, Whichever is Earlier | J14: 34999
A15: Thar Roxx | D15: Manual | E15: Diesel | F15: 3 Years OR 1 Lakh Kms, Whichever is Earlier | G15: 4th Year OR 1.2 Lakh Kms, Whichever is Earlier | H15: 199999 | I15: 4th & 5th Year OR 1.5 Lakh Kms, Whichever is Earlier | J15: 33999
A16: Thar Roxx | D16: Automatic | E16: Diesel | F16: 3 Years OR 1 Lakh Kms, Whichever is Earlier | G16: 4th Year OR 1.2 Lakh Kms, Whichever is Earlier | H16: 23999 | I16: 4th & 5th Year OR 1.5 Lakh Kms, Whichever is Earlier | J16: 35999
A17: BE6 FE | C17: Pack 2 | F17: 3 Years & Unlimited Kms | G17: 4th Year & Unlimited Kms | H17: 30999 | I17: 4th & 5th Year & Unlimited Kms | J17: 44999
A18: BE6 FE | C18: Pack 3 | F18: 3 Years & Unlimited Kms | G18: 4th Year & Unlimited Kms | H18: 35999 | I18: 4th & 5th Year & Unlimited Kms | J18: 49999
A19: BE6 | C19: Pack 1 | F19: 3 Years & Unlimited Kms | G19: 4th Year & Unlimited Kms | H19: 26999 | I19: 4th & 5th Year & Unlimited Kms | J19: 39999
A20: BE6 | C20: Pack 2 | F20: 3 Years & Unlimited Kms | G20: 4th Year & Unlimited Kms | H20: 30999 | I20: 4th & 5th Year & Unlimited Kms | J20: 44999
A21: BE6 | C21: Pack 3 | F21: 3 Years & Unlimited Kms | G21: 4th Year & Unlimited Kms | H21: 35999 | I21: 4th & 5th Year & Unlimited Kms | J21: 49999
A22: XEV9E | C22: Pack 1 | F22: 3 Years & Unlimited Kms | G22: 4th Year & Unlimited Kms | H22: 29999 | I22: 4th & 5th Year & Unlimited Kms | J22: 42999
A23: XEV9E | C23: Pack 2 | F23: 3 Years & Unlimited Kms | G23: 4th Year & Unlimited Kms | H23: 35999 | I23: 4th & 5th Year & Unlimited Kms | J23: 49999
A24: XEV9E | C24: Pack 3 | F24: 3 Years & Unlimited Kms | G24: 4th Year & Unlimited Kms | H24: 39999 | I24: 4th & 5th Year & Unlimited Kms | J24: 59999
A25: XEV9S | C25: Pack 1 79Kw | F25: 3 Years & Unlimited Kms | G25: 4th Year & Unlimited Kms | H25: 29999 | I25: 4th & 5th Year & Unlimited Kms | J25: 42999
A26: XEV9S | C26: Pack 1 59Kw | F26: 3 Years & Unlimited Kms | G26: 4th Year & Unlimited Kms | H26: 27499 | I26: 4th & 5th Year & Unlimited Kms | J26: 39499
A27: XEV9S | C27: Pack 2 | F27: 3 Years & Unlimited Kms | G27: 4th Year & Unlimited Kms | H27: 33499 | I27: 4th & 5th Year & Unlimited Kms | J27: 45999
A28: XEV9S | C28: Pack 3 | F28: 3 Years & Unlimited Kms | G28: 4th Year & Unlimited Kms | H28: 35999 | I28: 4th & 5th Year & Unlimited Kms | J28: 53999
A29: XEV9S | C29: Pack 3 Above | F29: 3 Years & Unlimited Kms | G29: 4th Year & Unlimited Kms | H29: 38999 | I29: 4th & 5th Year & Unlimited Kms | J29: 57999
A30: XUV 3XO | F30: 3 Years OR 1 Lakh Kms, Whichever is Earlier | G30: 4th Year OR 1.2 Lakh Kms, Whichever is Earlier | H30: 15000 | I30: 4th & 5th Year OR 1.5 Lakh Kms, Whichever is Earlier | J30: 22750
A31: XUV3XO EV | F31: 3 Years OR 1 Lakh Kms, Whichever is Earlier | G31: 4th Year OR 1.2 Lakh Kms, Whichever is Earlier | H31: 15000 | I31: 4th & 5th Year OR 1.5 Lakh Kms, Whichever is Earlier | J31: 22750
A32: XUV400 | F32: 3 Years OR 1 Lakh Kms, Whichever is Earlier | G32: 4th Year OR 1.0 Lakh Kms, Whichever is Earlier | H32: 22499 | I32: 4th & 5th Year OR 1.2 Lakh Kms, Whichever is Earlier | J32: 32499
A33: XUV7XO | D33: Manual | E33: Petrol | F33: 3 Years OR 1 Lakh Kms, Whichever is Earlier | G33: 4th Year OR 1.2 Lakh Kms, Whichever is Earlier | H33: 20999 | I33: 4th & 5th Year OR 1.5 Lakh Kms, Whichever is Earlier | J33: 37999
A34: XUV7XO | D34: Manual | E34: Diesel | F34: 3 Years OR 1 Lakh Kms, Whichever is Earlier | G34: 4th Year OR 1.2 Lakh Kms, Whichever is Earlier | H34: 23999 | I34: 4th & 5th Year OR 1.5 Lakh Kms, Whichever is Earlier | J34: 42999
A35: XUV7XO | D35: Automatic | E35: Petrol | F35: 3 Years OR 1 Lakh Kms, Whichever is Earlier | G35: 4th Year OR 1.2 Lakh Kms, Whichever is Earlier | H35: 23499 | I35: 4th & 5th Year OR 1.5 Lakh Kms, Whichever is Earlier | J35: 42999
A36: XUV7XO | D36: Automatic | E36: Diesel | F36: 3 Years OR 1 Lakh Kms, Whichever is Earlier | G36: 4th Year OR 1.2 Lakh Kms, Whichever is Earlier | H36: 22999 | I36: 4th & 5th Year OR 1.5 Lakh Kms, Whichever is Earlier | J36: 44999
A37: XUV7XO | C37: AX7L | D37: Automatic | E37: Petrol | F37: 3 Years OR 1 Lakh Kms, Whichever is Earlier | G37: 4th Year OR 1.2 Lakh Kms, Whichever is Earlier | H37: 31999 | I37: 4th & 5th Year OR 1.5 Lakh Kms, Whichever is Earlier | J37: 57999
A38: XUV7XO | C38: AX7L | D38: Automatic | E38: Diesel | F38: 3 Years OR 1 Lakh Kms, Whichever is Earlier | G38: 4th Year OR 1.2 Lakh Kms, Whichever is Earlier | H38: 31999 | I38: 4th & 5th Year OR 1.5 Lakh Kms, Whichever is Earlier | J38: 62499
A39: XUV7XO | C39: AX7L | D39: Manual | E39: Diesel | F39: 3 Years OR 1 Lakh Kms, Whichever is Earlier | G39: 4th Year OR 1.2 Lakh Kms, Whichever is Earlier | H39: 34999 | I39: 4th & 5th Year OR 1.5 Lakh Kms, Whichever is Earlier | J39: 63999
A40: ALFA LOAD DUO | F40: 3 Years OR 1 Lakh Kms, Whichever is Earlier
A41: ALFA LOAD PLUS | F41: 3 Years OR 1 Lakh Kms, Whichever is Earlier
A42: ALFA LOAD PLUS CNG | F42: 3 Years OR 1 Lakh Kms, Whichever is Earlier
A43: ALFA PASS DUO | F43: 3 Years OR 1 Lakh Kms, Whichever is Earlier
A44: ALFA PASSENGER CNG | F44: 3 Years OR 1 Lakh Kms, Whichever is Earlier
A45: ALFA PASSENGER COMFY | F45: 8 Months & Unlimited Kms
A46: ALFA PASSENGER DELUX | F46: 8 Months & Unlimited Kms
A47: E ALFA CARGO | F47: 1 Years & Unlimited Kms
A48: E ALFA PLUS | F48: 1.5 Years & Unlimited Kms
A49: E ALFA PLUS HT | F49: 1.5 Years & Unlimited Kms
A50: E ALFA SUPER | F50: 1 Years & Unlimited Kms
A51: JEETO CNG | F51: 3 Years OR 72000 kms, Whichever is Earlier
... A73: ZOR GRAND RE | F73: 5 Years OR 1.25 Lakh Kms, Whichever is Earlier

Sheet Insurance Co.
A1: Model | B1: Permit | C1: Insu Co. 1 | D1: Insu Co. 2 | E1: Insu Co. 3
A2: ALFA LOAD DUO | B2: Goods | C2: USGI
A3: ALFA LOAD PLUS | B3: Goods | C3: USGI
A4: ALFA LOAD PLUS CNG | B4: Goods | C4: USGI
A5: ALFA PASS DUO | B5: Passanger | C5: USGI
A6: ALFA PASSENGER CNG | B6: Passanger | C6: USGI
A7: ALFA PASSENGER COMFY | B7: Passanger | C7: USGI
A8: ALFA PASSENGER DELUX | B8: Passanger | C8: USGI
A9: BE6 | B9: Private | C9: USGI
A10: BE6 FE | B10: Private | C10: USGI
A11: BOLERO | B11: Private | C11: USGI
A12: BOLERO NEO | B12: Private | C12: USGI
A13: BOLERO NEO + | B13: Private | C13: USGI
... A65: ZOR GRAND RE | B65: Goods | C65: USGI
B69: Private
B70: Passanger
B71: Goods
B72: Misc

Sheet Insu Premium
A1: Inv | B1: IDV 1 | C1: IDV 2 | D1: IDV 3 | E1: IDV 1 | F1: IDV 2 | G1: IDV 3 | I1: Insu Co. | J1: Permit | K1: Wheels | L1: Fuel | M1: CC | N1: GVW | O1: Seatng | P1: Plan | Q1: OD - OD Factor | R1: OD - CNG / LPG Kit | S1: OD - IMT 23 | T1: TP Cover Basic | U1: TP Cover Per Pass | V1: TP Cover Bi Fuel Kit (CNG / LPG) | W1: TP - Compulsory PA COver Owner Driver | X1: TP - PA Cover for Passengers (1 Lakh Per Person) | Y1: TP - Legal Liability to Driver | Z1: TP - Legal Liability for Non Fare Paying Passengers | AA1: Add On - Nil Depreciation | AB1: Add On - Cosnumables | AC1: Add On - Engine Protect | AD1: Add On - Battery Protect (Including Motor, Charger & Adapter) | AE1: Add On - Battery Protect (Including Motor) | AF1: Add On - Battery Protect | AG1: Add On - Charger & Adapter Cover | AH1: Add On - Motor Protect | AI1: Add On - Tyre Protection | AJ1: Add On - Return to Invoice | AK1: Add On - Key Replacement | AL1: Add On - RSA | AM1: Add On - Personal Belongings | AN1: Add On - Daily Cash | AO1: Add On - Advance Assistance Cover | AP1: Add On - Medical Expenses Cover | AQ1: Add On - Towing
E2: 95% of Invoice | I2: USGI | J2: Private | K2: 4 | L2: ICE | M2: 0-1000 | P2: 1+3 | Q2: 0.03039 | T2: 6521 | AU2: Gioods | AV2: Private / Passenger
E3: 95% of Invoice | F3: 80% of Invoice | G3: 70% of Invoice | I3: USGI | J3: Private | K3: 4 | L3: ICE | M3: 0-1000 | P3: 3+3 | T3: 6521 | AU3: IDV | AV3: IDV
A4: 999900 | B4: =A4*95% -> 949905 | E4: 95% of Invoice | I4: USGI | J4: Private | K4: 4 | L4: ICE | M4: 1001-1500 | P4: 1+3 | Q4: 0.03191 | T4: 10640 | W4: 632 | X4: 150 Per Seat | AA4: =3325/$B4 -> 0.00350035 | AB4: =950/$B4 -> 0.0010001 | AC4: =1900/$B4 -> 0.0020002 | AI4: =2850/$B4 -> 0.0030003 | AJ4: =1425/$B4 -> 0.00150015 | AK4: 300 | AL4: 750 | AM4: 250 | AN4: 250 | AO4: 950 | AP4: 750 | AQ4: 300 | AU4: OD | AV4: OD
A5: 999900 | B5: =A5*95% -> 949905 | C5: =A5*80% -> 799920 | D5: =A5*70% -> 699930 | E5: 95% of Invoice | F5: 80% of Invoice | G5: 70% of Invoice | I5: USGI | J5: Private | K5: 4 | L5: ICE | M5: 1001-1500 | P5: 3+3 | T5: 10640 | AU5: OD DIsc | AV5: OD DIsc
A6: 1699900 | B6: =A6*95% -> 1614905 | E6: 95% of Invoice | I6: USGI | J6: Private | K6: 4 | L6: ICE | M6: >1500 | P6: 1+3 | Q6: 0.03343 | T6: 24596 | W6: 632 | X6: 150 Per Seat | AA6: =5653/$B6 -> 0.0035005155 | AB6: =1615/$B6 -> 0.0010000588 | AC6: =3230/$B6 -> 0.0020001177 | AI6: =4845/$B6 -> 0.0030001765 | AJ6: =2423/$B6 -> 0.0015003979 | AK6: 300 | AL6: 750 | AM6: 250 | AN6: 250 | AO6: 950 | AP6: 750 | AQ6: 300 | AU6: OD After Disc | AV6: OD After Disc
E7: 95% of Invoice | F7: 80% of Invoice | G7: 70% of Invoice | I7: USGI | J7: Private | K7: 4 | L7: ICE | M7: >1500 | P7: 3+3 | T7: 24596 | AU7: LPG CNG KiT | AV7: LPG CNG KiT
E8: 95% of Invoice | I8: USGI | J8: Private | K8: 4 | L8: EV | M8: < 30KW | P8: 1+3 | Q8: 0.03039 | T8: 5543 | AU8: IMT 23 | AV8: IMT 23
E9: 95% of Invoice | F9: 80% of Invoice | G9: 70% of Invoice | I9: USGI | J9: Private | K9: 4 | L9: EV | M9: < 30KW | P9: 3+3 | T9: 5543 | AU9: Total OD | AV9: Total OD
E10: 95% of Invoice | I10: USGI | J10: Private | K10: 4 | L10: EV | M10: 30 - 65 KW | P10: 1+3 | Q10: 0.03191 | T10: 9044
E11: 95% of Invoice | F11: 80% of Invoice | G11: 70% of Invoice | I11: USGI | J11: Private | K11: 4 | L11: EV | M11: 30 - 65 KW | P11: 3+3 | T11: 9044 | AU11: Add On Premium | AV11: Add On Premium
A12: 1749000 | B12: =A12*95% -> 1661550 | C12: =A12*80% -> 1399200 | D12: =A12*70% -> 1224300 | E12: 95% of Invoice | I12: USGI | J12: Private | K12: 4 | L12: EV | M12: >65 KW | P12: 1+3 | Q12: 0.03343 | T12: 20907 | W12: 632 | X12: 150 Per Seat | AA12: =4985/$B12 -> 0.0030002106 | AB12: =1662/$B12 -> 0.0010002708 | AF12: =1662/$B12 -> 0.0010002708 | AG12: =1662/$B12 -> 0.0010002708 | AH12: =1662/$B12 -> 0.0010002708 | AI12: =2493/$B12 -> 0.0015004062 | AJ12: =2493/$B12 -> 0.0015004062 | AK12: 500 | AL12: 750 | AM12: 500 | AN12: 500 | AO12: 950 | AP12: 750 | AQ12: 500 | AU12: Net OD Premium (A) | AV12: Net OD Premium (A)
E13: 95% of Invoice | F13: 80% of Invoice | G13: 70% of Invoice | I13: USGI | J13: Private | K13: 4 | L13: EV | M13: >65 KW | P13: 3+3 | T13: 20907
E14: 95% of Invoice | I14: USGI | J14: Passenger | K14: 4 | L14: ICE | M14: 0-1000 | O14: 1 to 7 | P14: 1+1 | Q14: 0.03191 | T14: 6040 | U14: 1162 x (Setat -1) | AU14: TP Basic Cover | AV14: TP Basic Cover
A15: 895600 | B15: =A15*95% -> 850820 | E15: 95% of Invoice | I15: USGI | J15: Passenger | K15: 4 | L15: ICE | M15: 1001-1500 | O15: 1 to 7 | P15: 1+1 | Q15: 0.03351 | T15: 7940 | U15: 978 x (Setat -1) | W15: 225 | Y15: 50 | AA15: =2978/$B15 -> 0.0035001528 | AB15: =851/$B15 -> 0.0010002116 | AC15: =1702/$B15 -> 0.0020004231 | AI15: =2553/$B15 -> 0.0030006347 | AJ15: =1277/$B15 -> 0.001500905 | AK15: 500 | AL15: 999 | AU15: TP Cover (Per Pass) | AV15: TP Cover (Per Pass)
A16: 1699900 | B16: =A16*95% -> 1614905 | E16: 95% of Invoice | I16: USGI | J16: Passenger | K16: 4 | L16: ICE | M16: >1500 | O16: 1 to 7 | P16: 1+1 | Q16: 0.0351 | T16: 10523 | U16: 1117 x (Setat -1) | W16: 225 | Y16: 50 | AA16: =5653/$B16 -> 0.0035005155 | AB16: =1615/$B16 -> 0.0010000588 | AC16: =3230/$B16 -> 0.0020001177 | AI16: =4845/$B16 -> 0.0030001765 | AJ16: =2423/$B16 -> 0.0015003979 | AK16: 500 | AL16: 999 | AU16: TP Cover - Bi Fuel Kit (CNG / LPG) | AV16: TP Cover - Bi Fuel Kit (CNG / LPG)
E17: 95% of Invoice | I17: USGI | J17: Passenger | K17: 4 | L17: EV | M17: < 30KW | O17: 1 to 7 | P17: 1+1 | Q17: 0.03191 | T17: 5134 | U17: 988 x (Setat -1) | AU17: TP - Compulsory PA Cover Owner Driver | AV17: TP - Compulsory PA Cover Owner Driver
E18: 95% of Invoice | I18: USGI | J18: Passenger | K18: 4 | L18: EV | M18: 30 - 65 KW | O18: 1 to 7 | P18: 1+1 | Q18: 0.03351 | T18: 6749 | U18: 831 x (Setat -1) | AU18: TP - PA Cover for Passengers (1 Lakh Per Person) | AV18: TP - PA Cover for Passengers (1 Lakh Per Person)
A19: 1749000 | B19: =A19*95% -> 1661550 | E19: 95% of Invoice | I19: USGI | J19: Passenger | K19: 4 | L19: EV | M19: >65 KW | O19: 1 to 7 | P19: 1+1 | Q19: 0.0351 | T19: 8945 | U19: 949 x (Setat -1) | W19: 225 | Y19: 50 | AA19: =5816/$B19 -> 0.0035003461 | AB19: =1662/$B19 -> 0.0010002708 | AF19: =4154/$B19 -> 0.0025000752 | AG19: =1662/$B19 -> 0.0010002708 | AH19: =1662/$B19 -> 0.0010002708 | AI19: =4985/$B19 -> 0.0030002106 | AJ19: =2493/$B19 -> 0.0015004062 | AK19: =4154/$B19 -> 0.0025000752 | AL19: 999 | AU19: TP - Legal Liability to Driver | AV19: TP - Legal Liability to Driver
A20: 310039 | B20: =A20*95% -> 294537.05 | E20: 95% of Invoice | I20: USGI | J20: Passenger | K20: 3 | L20: ICE | O20: 1 to 7 | P20: 1+1 | Q20: 0.0126 | R20: 5% x OD | S20: 15% x (OD + LPG) | T20: 2539 | U20: 1214 x (Setat -1) | V20: 60 | W20: 225 | Y20: 50 | AA20: =1031/$B20 -> 0.0035004085 | AB20: =295/$B20 -> 0.0010015718 | AC20: =590/$B20 -> 0.0020031436 | AI20: =884/$B20 -> 0.0030013202 | AJ20: =442/$B20 -> 0.0015006601 | AK20: 500 | AL20: 999 | AU20: TP - Legal Liability for Non Fare Paying Passengers | AV20: TP - Legal Liability for Non Fare Paying Passengers
E21: 95% of Invoice | I21: USGI | J21: Passenger | K21: 3 | L21: ICE | O21: 8 to 18 | P21: 1+1 | Q21: 0.01759 | T21: 6763 | U21: 1349 x (Setat -1) | AU21: Net TP Premium (B) | AV21: Net TP Premium (B)
A22: 393837 | B22: =A22*95% -> 374145.15 | E22: 95% of Invoice | I22: USGI | J22: Passenger | K22: 3 | L22: EV | O22: 1 to 7 | P22: 1+1 | Q22: 0.0126 | S22: 15% x OD | T22: 1648 | U22: 789 x (Setat -1) | W22: 225 | Y22: 50 | AA22: =1310/$B22 -> 0.0035013149 | AB22: =375/$B22 -> 0.0010022848 | AI22: =1123/$B22 -> 0.0030015089 | AJ22: =562/$B22 -> 0.0015020908 | AK22: 500 | AL22: 999
A23: 1019000 | B23: =A23*95% -> 968050 | E23: 95% of Invoice | I23: USGI | J23: Goods | K23: 4 | L23: ICE | N23: 0-7500 | P23: 1+1 | Q23: 0.01726 | R23: 5% x OD | S23: 15% x (OD + LPG) | T23: 16049 | V23: 60 | W23: 225 | Y23: 50 | Z23: 75 x (Seat -1) | AA23: =3679/$B23 -> 0.0038004235 | AB23: =969/$B23 -> 0.0010009814 | AC23: =1937/$B23 -> 0.0020009297 | AJ23: =2421/$B23 -> 0.0025009039 | AK23: 500 | AL23: 999 | AM23: 500 | AN23: 500 | AQ23: 500 | AU23: GST @ 18% on OD | AV23: GST @ 18%
A24: 322781 | B24: =A24*95% -> 306641.95 | E24: 95% of Invoice | I24: USGI | J24: Goods | K24: 3 | L24: ICE | N24: 0-7500 | P24: 1+1 | Q24: 0.0164 | R24: 5% x OD | S24: 15% x (OD + LPG) | T24: 4492 | V24: 60 | W24: 225 | Y24: 50 | AA24: =1166/$B24 -> 0.0038024804 | AB24: =307/$B24 -> 0.0010011676 | AC24: =614/$B24 -> 0.0020023353 | AJ24: =767/$B24 -> 0.0025012886 | AK24: 500 | AL24: 999 | AM24: 500 | AN24: 500 | AQ24: 500 | AU24: GST @ 6% on TP in Goods | AV24: GST Amount
A25: 806081 | B25: =A25*95% -> 765776.95 | E25: 95% of Invoice | I25: USGI | J25: Goods | K25: 4 | L25: EV | N25: 0-7500 | P25: 1+1 | Q25: 0.01726 | S25: 15% x OD | T25: 13642 | W25: 225 | Y25: 50 | Z25: 75 x (Seat -1) | AA25: =2910/$B25 -> 0.0038000621 | AB25: =766/$B25 -> 0.0010002913 | AJ25: =1915/$B25 -> 0.0025007282 | AK25: 500 | AL25: 999 | AM25: 500 | AN25: 500 | AQ25: 500 | AU25: GST Amount | AV25: Total Premium with GST
A26: 416827 | B26: =A26*95% -> 395985.65 | E26: 95% of Invoice | I26: USGI | J26: Goods | K26: 3 | L26: EV | N26: 0-7500 | P26: 1+1 | Q26: 0.0164 | S26: 15% x OD | T26: 3139 | W26: 225 | Y26: 50 | AA26: =1505/$B26 -> 0.0038006428 | AB26: =396/$B26 -> 0.0010000362 | AJ26: =990/$B26 -> 0.0025000906 | AK26: 500 | AL26: 999 | AM26: 500 | AN26: 500 | AQ26: 500 | AU26: Total Premium with GST
E27: 95% of Invoice | I27: USGI | J27: Misc | P27: 1+1 | Q27: 0.0119 | T27: 7267 | W27: 225 | Y27: 50

Sheet RTO
A1: Permit | B1: Wheels | C1: Reg Type | D1: Body Type | E1: GVW | F1: Seater | G1: Fuel | H1: CC | I1: Assesable Value | J1: Outside State - TRC Only | K1: Tax Factor | L1: Tax Slab | M1: Surcharge | N1: Hypothecation | O1: Green Tax | P1: Registration Fee | Q1: Duplicate Tax Card | R1: Fitness | S1: Penalty | T1: Total Amount
A2: Goods | B2: 4 | C2: Regular | D2: Complete | E2: 0-3000 | G2: Diesel | J2: 1000 | K2: % of Rounded Up ESR | L2: 0.1 | M2: 12.5% of Tax | N2: 1500 | O2: 1500 | P2: 600 | Q2: 100 | R2: 0 | T2: Sum of All
A3: Goods | B3: 4 | C3: Regular | D3: Complete | E3: 0-3000 | G3: Petrol | J3: 1000 | K3: % of Rounded Up ESR | L3: 0.1 | M3: 12.5% of Tax | N3: 1500 | O3: 1500 | P3: 600 | Q3: 100 | R3: 0 | T3: Sum of All
A4: Goods | B4: 4 | C4: Regular | D4: Complete | E4: 0-3000 | G4: Electric | J4: 1000 | K4: % of Rounded Up ESR | L4: 0 | M4: 0% of Tax | N4: 1500 | O4: 0 | P4: 600 | Q4: 100 | R4: 0 | T4: Sum of All
A5: Goods | B5: 4 | C5: Regular | D5: Complete | E5: 3001 - 16500 | G5: Diesel | J5: 1000 | K5: % of Rounded Up ESR | L5: 0.11 | M5: 12.5% of Tax | N5: 1500 | O5: 1500 | P5: 600 | Q5: 100 | R5: 0 | T5: Sum of All
A6: Goods | B6: 4 | C6: Regular | D6: Complete | E6: 3001 - 16500 | G6: Petrol | J6: 1000 | K6: % of Rounded Up ESR | L6: 0.11 | M6: 12.5% of Tax | N6: 1500 | O6: 1500 | P6: 600 | Q6: 100 | R6: 0 | T6: Sum of All
A7: Goods | B7: 4 | C7: Regular | D7: Complete | E7: 3001 - 16500 | G7: Electric | J7: 1000 | K7: % of Rounded Up ESR | L7: 0 | M7: 0% of Tax | N7: 1500 | O7: 0 | P7: 600 | Q7: 100 | R7: 0 | T7: Sum of All
A8: Goods | B8: 3 | C8: Regular | D8: Complete | G8: Diesel | J8: 1000 | K8: % of Rounded Up ESR | L8: 0.09 | M8: 12.5% of Tax | N8: 1500 | O8: 500 | P8: 600 | Q8: 100 | R8: 0 | T8: Sum of All
A9: Goods | B9: 3 | C9: Regular | D9: Complete | G9: Petrol | J9: 1000 | K9: % of Rounded Up ESR | L9: 0.09 | M9: 12.5% of Tax | N9: 1500 | O9: 500 | P9: 600 | Q9: 100 | R9: 0 | T9: Sum of All
A10: Goods | B10: 3 | C10: Regular | D10: Complete | G10: Electric | J10: 1000 | K10: % of Rounded Up ESR | L10: 0 | M10: 0% of Tax | N10: 1500 | O10: 0 | P10: 600 | Q10: 100 | R10: 0 | T10: Sum of All
A11: Goods | B11: 4 | C11: Regular | D11: CBC | E11: 0-3000 | G11: Diesel | J11: 1000 | K11: % of Rounded Up ESR | L11: 0.1 | M11: 12.5% of Tax | N11: 1500 | O11: 1500 | P11: 600 | Q11: 100 | R11: 0 | S11: 5000 | T11: Sum of All
A12: Goods | B12: 4 | C12: Regular | D12: CBC | E12: 0-3000 | G12: Petrol | J12: 1000 | K12: % of Rounded Up ESR | L12: 0.1 | M12: 12.5% of Tax | N12: 1500 | O12: 1500 | P12: 600 | Q12: 100 | R12: 0 | S12: 5000 | T12: Sum of All
A13: Goods | B13: 4 | C13: Regular | D13: CBC | E13: 0-3000 | G13: Electric | J13: 1000 | K13: % of Rounded Up ESR | L13: 0 | M13: 0% of Tax | N13: 1500 | O13: 0 | P13: 600 | Q13: 100 | R13: 0 | S13: 5000 | T13: Sum of All
A14: Goods | B14: 4 | C14: Regular | D14: CBC | E14: 3001 - 16500 | G14: Diesel | J14: 1000 | K14: % of Rounded Up ESR | L14: 0.11 | M14: 12.5% of Tax | N14: 1500 | O14: 1500 | P14: 600 | Q14: 100 | R14: 0 | S14: 5000 | T14: Sum of All
A15: Goods | B15: 4 | C15: Regular | D15: CBC | E15: 3001 - 16500 | G15: Petrol | J15: 1000 | K15: % of Rounded Up ESR | L15: 0.11 | M15: 12.5% of Tax | N15: 1500 | O15: 1500 | P15: 600 | Q15: 100 | R15: 0 | S15: 5000 | T15: Sum of All
A16: Goods | B16: 4 | C16: Regular | D16: CBC | E16: 3001 - 16500 | G16: Electric | J16: 1000 | K16: % of Rounded Up ESR | L16: 0 | M16: 0% of Tax | N16: 1500 | O16: 0 | P16: 600 | Q16: 100 | R16: 0 | S16: 5000 | T16: Sum of All
A17: Goods | B17: 3 | C17: Regular | D17: CBC | G17: Diesel | J17: 1000 | K17: % of Rounded Up ESR | L17: 0.09 | M17: 12.5% of Tax | N17: 1500 | O17: 500 | P17: 600 | Q17: 100 | R17: 0 | S17: 5000 | T17: Sum of All
A18: Goods | B18: 3 | C18: Regular | D18: CBC | G18: Petrol | J18: 1000 | K18: % of Rounded Up ESR | L18: 0.09 | M18: 12.5% of Tax | N18: 1500 | O18: 500 | P18: 600 | Q18: 100 | R18: 0 | S18: 5000 | T18: Sum of All
A19: Goods | B19: 3 | C19: Regular | D19: CBC | G19: Electric | J19: 1000 | K19: % of Rounded Up ESR | L19: 0 | M19: 0% of Tax | N19: 1500 | O19: 0 | P19: 600 | Q19: 100 | R19: 0 | S19: 5000 | T19: Sum of All
A20: Passenger | B20: 3 | C20: Regular | F20: <4 | G20: Diesel | J20: 1000 | K20: Fixed | L20: 3000 | M20: 12.5% of Tax | N20: 1500 | O20: 500 | P20: 600 | Q20: 100 | R20: 0 | S20: 0 | T20: Sum of All
A21: Passenger | B21: 3 | C21: Regular | F21: <4 | G21: Petrol | J21: 1000 | K21: Fixed | L21: 3000 | M21: 12.5% of Tax | N21: 1500 | O21: 500 | P21: 600 | Q21: 100 | R21: 0 | S21: 0 | T21: Sum of All
A22: Passenger | B22: 3 | C22: Regular | F22: <4 | G22: Electric | J22: 1000 | K22: % of Rounded Up ESR | L22: 0 | M22: 0% of Tax | N22: 1500 | O22: 0 | P22: 600 | Q22: 100 | R22: 0 | S22: 0 | T22: Sum of All
A23: Passenger | B23: 3 | C23: Regular | F23: 4 | G23: Diesel | J23: 1000 | K23: Fixed | L23: 6000 | M23: 12.5% of Tax | N23: 1500 | O23: 500 | P23: 600 | Q23: 100 | R23: 0 | S23: 0 | T23: Sum of All
A24: Passenger | B24: 3 | C24: Regular | F24: 4 | G24: Petrol | J24: 1000 | K24: Fixed | L24: 6000 | M24: 12.5% of Tax | N24: 1500 | O24: 500 | P24: 600 | Q24: 100 | R24: 0 | S24: 0 | T24: Sum of All
A25: Passenger | B25: 3 | C25: Regular | F25: 4 | G25: Electric | J25: 1000 | K25: % of Rounded Up ESR | L25: 0 | M25: 0% of Tax | N25: 1500 | O25: 0 | P25: 600 | Q25: 100 | R25: 0 | S25: 0 | T25: Sum of All
A26: Passenger | B26: 3 | C26: Regular | F26: >4 | G26: Diesel | J26: 1000 | K26: Fixed | L26: 8000 | M26: 12.5% of Tax | N26: 1500 | O26: 500 | P26: 600 | Q26: 100 | R26: 0 | S26: 0 | T26: Sum of All
A27: Passenger | B27: 3 | C27: Regular | F27: >4 | G27: Petrol | J27: 1000 | K27: Fixed | L27: 8000 | M27: 12.5% of Tax | N27: 1500 | O27: 500 | P27: 600 | Q27: 100 | R27: 0 | S27: 0 | T27: Sum of All
A28: Passenger | B28: 3 | C28: Regular | F28: >4 | G28: Electric | J28: 1000 | K28: % of Rounded Up ESR | L28: 0 | M28: 0% of Tax | N28: 1500 | O28: 0 | P28: 600 | Q28: 100 | R28: 0 | S28: 0 | T28: Sum of All
A29: Taxi | B29: 4 | C29: Regular | F29: 0-13 | J29: 1000 | K29: % of Rounded Up ESR | L29: 0.1 | M29: 12.5% of Tax | N29: 1500 | O29: 1500 | P29: 600 | Q29: 100 | R29: 0 | S29: 0 | T29: Sum of All
A30: Ambulance | B30: 4 | C30: Regular | J30: 1000 | K30: % of Rounded Up ESR | L30: 0 | M30: 0% of Tax | N30: 1500 | O30: 1500 | P30: 600 | Q30: 100 | R30: 0 | S30: 0 | T30: Sum of All
A31: Private | B31: 4 | C31: Regular | F31: ANY | G31: Diesel | H31: 0-800 | J31: 1000 | K31: % of Rounded Up ESR | L31: 0.08 | M31: 12.5% of Tax | N31: 1500 | P31: 600 | Q31: 100 | S31: 0 | T31: Sum of All
A32: Private | B32: 4 | C32: Regular | F32: ANY | G32: Petrol | H32: 0-800 | J32: 1000 | K32: % of Rounded Up ESR | L32: 0.06 | M32: 12.5% of Tax | N32: 1500 | P32: 600 | Q32: 100 | S32: 0 | T32: Sum of All
A33: Private | B33: 4 | C33: Regular | F33: ANY | G33: Diesel | H33: 801-1200 | J33: 1000 | K33: % of Rounded Up ESR | L33: 0.12 | M33: 12.5% of Tax | N33: 1500 | O33: 2500 | P33: 600 | Q33: 100 | R33: 0 | S33: 0 | T33: Sum of All
A34: Private | B34: 4 | C34: Regular | F34: ANY | G34: Petrol | H34: 801-1200 | J34: 1000 | K34: % of Rounded Up ESR | L34: 0.09 | M34: 12.5% of Tax | N34: 1500 | O34: 2500 | P34: 600 | Q34: 100 | R34: 0 | S34: 0 | T34: Sum of All
A35: Private | B35: 4 | C35: Regular | F35: ANY | G35: Diesel | H35: >1200 | J35: 1000 | K35: % of Rounded Up ESR | L35: 0.12 | M35: 12.5% of Tax | N35: 1500 | O35: 7500 | P35: 600 | Q35: 100 | R35: 0 | S35: 0 | T35: Sum of All
A36: Private | B36: 4 | C36: Regular | F36: ANY | G36: Petrol | H36: >1200 | J36: 1000 | K36: % of Rounded Up ESR | L36: 0.1 | M36: 12.5% of Tax | N36: 1500 | O36: 1500 | P36: 600 | Q36: 100 | R36: 0 | S36: 0 | T36: Sum of All
A37: Private | B37: 4 | C37: Regular | F37: ANY | G37: Electric | J37: 1000 | K37: % of Rounded Up ESR | L37: 0 | M37: 0% of Tax | N37: 1500 | O37: 0 | P37: 600 | Q37: 100 | R37: 0 | S37: 0 | T37: Sum of All
A38: Private | B38: 4 | C38: BH | G38: Diesel | I38: 0-999999 | J38: 1000 | K38: % of Rounded Up Ass Value + Dlr Mgn WO GST | L38: (10% * 1.25 * 2) / 15 | M38: 0% of Tax | N38: 1500 | O38: 2500 | P38: 600 | Q38: 100 | R38: 0 | S38: 2500 | T38: Sum of All
A39: Private | B39: 4 | C39: BH | G39: Petrol | I39: 0-999999 | J39: 1000 | K39: % of Rounded Up Ass Value + Dlr Mgn WO GST | L39: (8% * 1.25 * 2) / 15 | M39: 0% of Tax | N39: 1500 | O39: 2500 | P39: 600 | Q39: 100 | R39: 0 | S39: 2500 | T39: Sum of All
A40: Private | B40: 4 | C40: BH | G40: Electric | I40: 0-999999 | J40: 1000 | K40: % of Rounded Up Ass Value + Dlr Mgn WO GST | L40: (6% * 1.25 * 2) / 15 | M40: 0% of Tax | N40: 1500 | O40: 0 | P40: 600 | Q40: 100 | R40: 0 | S40: 2500 | T40: Sum of All
A41: Private | B41: 4 | C41: BH | G41: Diesel | I41: 1000000 - 200000 | J41: 1000 | K41: % of Rounded Up Ass Value + Dlr Mgn WO GST | L41: (12% * 1.25 * 2 ) /15 | M41: 0% of Tax | N41: 1500 | O41: 2500 | P41: 600 | Q41: 100 | R41: 0 | S41: 2500 | T41: Sum of All
A42: Private | B42: 4 | C42: BH | G42: Petrol | I42: 1000000 - 200000 | J42: 1000 | K42: % of Rounded Up Ass Value + Dlr Mgn WO GST | L42: (10% * 1.25 * 2) / 15 | M42: 0% of Tax | N42: 1500 | O42: 2500 | P42: 600 | Q42: 100 | R42: 0 | S42: 2500 | T42: Sum of All
A43: Private | B43: 4 | C43: BH | G43: Electric | I43: 1000000 - 200000 | J43: 1000 | K43: % of Rounded Up Ass Value + Dlr Mgn WO GST | L43: (8% * 1.25 * 2) / 15 | M43: 0% of Tax | N43: 1500 | O43: 0 | P43: 600 | Q43: 100 | R43: 0 | S43: 2500 | T43: Sum of All
A44: Private | B44: 4 | C44: BH | G44: Diesel | I44: Above 2000000 | J44: 1000 | K44: % of Rounded Up Ass Value + Dlr Mgn WO GST | L44: (14% * 1.25 * 2 ) / 15 | M44: 0% of Tax | N44: 1500 | O44: 2500 | P44: 600 | Q44: 100 | R44: 0 | S44: 2500 | T44: Sum of All
A45: Private | B45: 4 | C45: BH | G45: Petrol | I45: Above 2000000 | J45: 1000 | K45: % of Rounded Up Ass Value + Dlr Mgn WO GST | L45: (12% * 1.25 * 2) / 15 | M45: 0% of Tax | N45: 1500 | O45: 2500 | P45: 600 | Q45: 100 | R45: 0 | S45: 2500 | T45: Sum of All
A46: Private | B46: 4 | C46: BH | G46: Electric | I46: Above 2000000 | J46: 1000 | K46: % of Rounded Up Ass Value + Dlr Mgn WO GST | L46: (10% * 1.25 * 2) / 15 | M46: 0% of Tax | N46: 1500 | O46: 0 | P46: 600 | Q46: 100 | R46: 0 | S46: 2500 | T46: Sum of All

Sheet Dealer Charges - Segment Wise
A1: Segment | B1: Permit | C1: Model | D1: Incidental Charges | E1: FastTag | F1: TRC | G1: RTO Tape | H1: COD Charges
A2: PV | B2: Private | C2: Any | E2: 600 | F2: 1000 | G2: 1299 | H2: 42000
A3: PV | B3: Passenger | C3: Any
A4: CV | C4: Any | E4: 600 | F4: 1000 | G4: 1299 | H4: 42000
A5: LMM | C5: Any | D5: 5900 | E5: 600 | F5: 1000 | G5: 1299 | H5: 42000
A6: BEV | C6: Any | E6: 600 | F6: 1000 | G6: 1299 | H6: 42000
